<?xml version="1.0" encoding="UTF-8"?>
<SunopsisExport>
<Admin RepositoryVersion="05.02.02.07" IsLegacyIdCompatible="false" />
<Encryption algorithm="AES" keyLength="128" exportKeyHash="" keyVect="zrWjuPec1VwFvriOOI2Liw==" exportKeySalt="1e180108-efd8-41cb-9eed-4a0fea9d25fb" containsCipherText="false"/>
<Object class="com.sunopsis.dwg.dbobj.SnpTable">
		<Field name="ExtVersion" type="java.lang.String">null</Field>
	<Field name="FileDecSep" type="java.lang.String">null</Field>
	<Field name="FileEncField" type="java.lang.String">null</Field>
	<Field name="FileEscChar" type="java.lang.String">null</Field>
	<Field name="FileFirstRow" type="com.sunopsis.sql.DbInt"><![CDATA[null]]></Field>
	<Field name="FileFormat" type="java.lang.String">null</Field>
	<Field name="FileNullValue" type="java.lang.String">null</Field>
	<Field name="FileSepColl" type="java.lang.String">null</Field>
	<Field name="FileSepField" type="java.lang.String">null</Field>
	<Field name="FileSepMap" type="java.lang.String">null</Field>
	<Field name="FileSepRow" type="java.lang.String">null</Field>
	<Field name="FirstDate" type="java.sql.Timestamp"><![CDATA[2018-05-20 00:30:51.0]]></Field>
	<Field name="FirstUser" type="java.lang.String"><![CDATA[SUPERVISOR]]></Field>
	<Field name="GlobalId" type="java.lang.String"><![CDATA[5bef048a-c388-40bc-a2a0-a7c007baf5f9]]></Field>
	<Field name="HiveBuckets" type="com.sunopsis.sql.DbInt"><![CDATA[null]]></Field>
	<Field name="HiveLocation" type="java.lang.String">null</Field>
	<Field name="HiveRowFormat" type="java.lang.String">null</Field>
	<Field name="IndChange" type="java.lang.String">null</Field>
	<Field name="IndErrDel" type="java.lang.String">null</Field>
	<Field name="IndFilePosAuto" type="java.lang.String">null</Field>
	<Field name="IndHiveManaged" type="java.lang.String">null</Field>
	<Field name="IndHiveNative" type="java.lang.String">null</Field>
	<Field name="IndJrn" type="java.lang.String"><![CDATA[0]]></Field>
	<Field name="IndShow" type="java.lang.String"><![CDATA[1]]></Field>
	<Field name="IndWs" type="java.lang.String">null</Field>
	<Field name="InputFormat" type="java.lang.String">null</Field>
	<Field name="IntVersion" type="com.sunopsis.sql.DbInt"><![CDATA[4]]></Field>
	<Field name="IMod" type="com.sunopsis.sql.DbInt"><![CDATA[38]]></Field>
	<Field name="IScBaseTable" type="com.sunopsis.sql.DbInt"><![CDATA[null]]></Field>
	<Field name="IScOrigTable" type="com.sunopsis.sql.DbInt"><![CDATA[null]]></Field>
	<Field name="IScTable" type="com.sunopsis.sql.DbInt"><![CDATA[null]]></Field>
	<Field name="ISubModel" type="com.sunopsis.sql.DbInt"><![CDATA[131]]></Field>
	<Field name="ITable" type="com.sunopsis.sql.DbInt"><![CDATA[1474]]></Field>
	<Field name="ITableFormatType" type="com.sunopsis.sql.DbInt"><![CDATA[null]]></Field>
	<Field name="ITxtDesc" type="com.sunopsis.sql.DbInt"><![CDATA[null]]></Field>
	<Field name="ITxtWsdl" type="com.sunopsis.sql.DbInt"><![CDATA[null]]></Field>
	<Field name="JrnOrder" type="com.sunopsis.sql.DbInt"><![CDATA[null]]></Field>
	<Field name="LastDate" type="java.sql.Timestamp"><![CDATA[2018-05-21 01:08:04.0]]></Field>
	<Field name="LastUser" type="java.lang.String"><![CDATA[SUPERVISOR]]></Field>
	<Field name="OlapType" type="java.lang.String">null</Field>
	<Field name="OutputFormat" type="java.lang.String">null</Field>
	<Field name="PartitionMeth" type="java.lang.String">null</Field>
	<Field name="ResName" type="java.lang.String"><![CDATA[GER_EVENT_RESTRAINT_OTHER]]></Field>
	<Field name="RCount" type="com.sunopsis.sql.DbInt"><![CDATA[null]]></Field>
	<Field name="SchemaFile" type="java.lang.String">null</Field>
	<Field name="ScOrigTableTag" type="java.lang.String">null</Field>
	<Field name="Serde" type="java.lang.String">null</Field>
	<Field name="SerdeProp" type="java.lang.String">null</Field>
	<Field name="StorageHandler" type="java.lang.String">null</Field>
	<Field name="StorageProp" type="java.lang.String">null</Field>
	<Field name="SubPartitionMeth" type="java.lang.String">null</Field>
	<Field name="TableAlias" type="java.lang.String"><![CDATA[GER_EVENT_RESTRAINT_OTHER]]></Field>
	<Field name="TableName" type="java.lang.String"><![CDATA[GER_EVENT_RESTRAINT_OTHER]]></Field>
	<Field name="TableProp" type="java.lang.String">null</Field>
	<Field name="TableType" type="java.lang.String"><![CDATA[T]]></Field>
	<Field name="WsEntityName" type="java.lang.String">null</Field>
	<Field name="WsName" type="java.lang.String">null</Field>
</Object>
<Object class="com.sunopsis.dwg.dbobj.SnpCol">
		<Field name="Bytes" type="com.sunopsis.sql.DbInt"><![CDATA[0]]></Field>
	<Field name="CheckFlow" type="java.lang.String"><![CDATA[1]]></Field>
	<Field name="CheckStat" type="java.lang.String"><![CDATA[0]]></Field>
	<Field name="ColDecSep" type="java.lang.String">null</Field>
	<Field name="ColFormat" type="java.lang.String">null</Field>
	<Field name="ColHeading" type="java.lang.String"><![CDATA[ID]]></Field>
	<Field name="ColMandatory" type="java.lang.String"><![CDATA[1]]></Field>
	<Field name="ColName" type="java.lang.String"><![CDATA[ID]]></Field>
	<Field name="ColNullIfErr" type="java.lang.String">null</Field>
	<Field name="DataFormat" type="java.lang.String">null</Field>
	<Field name="DefValue" type="java.lang.String">null</Field>
	<Field name="ExtVersion" type="java.lang.String">null</Field>
	<Field name="FilePos" type="com.sunopsis.sql.DbInt"><![CDATA[null]]></Field>
	<Field name="FirstDate" type="java.sql.Timestamp"><![CDATA[2018-05-20 00:30:51.0]]></Field>
	<Field name="FirstUser" type="java.lang.String"><![CDATA[SUPERVISOR]]></Field>
	<Field name="GlobalId" type="java.lang.String"><![CDATA[b6441642-0ab0-4e6c-a2ef-de91e07cfbbf]]></Field>
	<Field name="HbaseEncoding" type="java.lang.String">null</Field>
	<Field name="HiveSortbyPos" type="com.sunopsis.sql.DbInt"><![CDATA[null]]></Field>
	<Field name="IndChange" type="java.lang.String"><![CDATA[U]]></Field>
	<Field name="IndHiveCluster" type="java.lang.String">null</Field>
	<Field name="IndHivePartition" type="java.lang.String">null</Field>
	<Field name="IndHiveSort" type="java.lang.String">null</Field>
	<Field name="IndHiveSortbyAsc" type="java.lang.String">null</Field>
	<Field name="IndIn" type="java.lang.String">null</Field>
	<Field name="IndOut" type="java.lang.String">null</Field>
	<Field name="IndWrite" type="java.lang.String"><![CDATA[1]]></Field>
	<Field name="IndWsInsert" type="java.lang.String"><![CDATA[1]]></Field>
	<Field name="IndWsSelect" type="java.lang.String"><![CDATA[1]]></Field>
	<Field name="IndWsUpdate" type="java.lang.String"><![CDATA[1]]></Field>
	<Field name="IntVersion" type="com.sunopsis.sql.DbInt"><![CDATA[4]]></Field>
	<Field name="ICol" type="com.sunopsis.sql.DbInt"><![CDATA[13464]]></Field>
	<Field name="ISrcCol" type="com.sunopsis.sql.DbInt"><![CDATA[null]]></Field>
	<Field name="ITable" type="com.sunopsis.sql.DbInt"><![CDATA[1474]]></Field>
	<Field name="ITxtColDesc" type="com.sunopsis.sql.DbInt"><![CDATA[null]]></Field>
	<Field name="LastDate" type="java.sql.Timestamp"><![CDATA[2018-05-21 01:08:04.0]]></Field>
	<Field name="LastUser" type="java.lang.String"><![CDATA[SUPERVISOR]]></Field>
	<Field name="Longc" type="com.sunopsis.sql.DbInt"><![CDATA[10]]></Field>
	<Field name="Pos" type="com.sunopsis.sql.DbInt"><![CDATA[1]]></Field>
	<Field name="RecCodeList" type="java.lang.String">null</Field>
	<Field name="Scalec" type="com.sunopsis.sql.DbInt"><![CDATA[0]]></Field>
	<Field name="ScdColType" type="java.lang.String">null</Field>
	<Field name="SourceDt" type="java.lang.String"><![CDATA[NUMBER]]></Field>
</Object>
<Object class="com.sunopsis.dwg.dbobj.SnpCol">
		<Field name="Bytes" type="com.sunopsis.sql.DbInt"><![CDATA[0]]></Field>
	<Field name="CheckFlow" type="java.lang.String"><![CDATA[1]]></Field>
	<Field name="CheckStat" type="java.lang.String"><![CDATA[0]]></Field>
	<Field name="ColDecSep" type="java.lang.String">null</Field>
	<Field name="ColFormat" type="java.lang.String">null</Field>
	<Field name="ColHeading" type="java.lang.String"><![CDATA[SUMMARY]]></Field>
	<Field name="ColMandatory" type="java.lang.String"><![CDATA[0]]></Field>
	<Field name="ColName" type="java.lang.String"><![CDATA[SUMMARY]]></Field>
	<Field name="ColNullIfErr" type="java.lang.String">null</Field>
	<Field name="DataFormat" type="java.lang.String">null</Field>
	<Field name="DefValue" type="java.lang.String">null</Field>
	<Field name="ExtVersion" type="java.lang.String">null</Field>
	<Field name="FilePos" type="com.sunopsis.sql.DbInt"><![CDATA[null]]></Field>
	<Field name="FirstDate" type="java.sql.Timestamp"><![CDATA[2018-05-20 00:30:51.0]]></Field>
	<Field name="FirstUser" type="java.lang.String"><![CDATA[SUPERVISOR]]></Field>
	<Field name="GlobalId" type="java.lang.String"><![CDATA[2b232b05-3055-45fa-9513-d6a05f4856f7]]></Field>
	<Field name="HbaseEncoding" type="java.lang.String">null</Field>
	<Field name="HiveSortbyPos" type="com.sunopsis.sql.DbInt"><![CDATA[null]]></Field>
	<Field name="IndChange" type="java.lang.String"><![CDATA[U]]></Field>
	<Field name="IndHiveCluster" type="java.lang.String">null</Field>
	<Field name="IndHivePartition" type="java.lang.String">null</Field>
	<Field name="IndHiveSort" type="java.lang.String">null</Field>
	<Field name="IndHiveSortbyAsc" type="java.lang.String">null</Field>
	<Field name="IndIn" type="java.lang.String">null</Field>
	<Field name="IndOut" type="java.lang.String">null</Field>
	<Field name="IndWrite" type="java.lang.String"><![CDATA[1]]></Field>
	<Field name="IndWsInsert" type="java.lang.String"><![CDATA[1]]></Field>
	<Field name="IndWsSelect" type="java.lang.String"><![CDATA[1]]></Field>
	<Field name="IndWsUpdate" type="java.lang.String"><![CDATA[1]]></Field>
	<Field name="IntVersion" type="com.sunopsis.sql.DbInt"><![CDATA[4]]></Field>
	<Field name="ICol" type="com.sunopsis.sql.DbInt"><![CDATA[13465]]></Field>
	<Field name="ISrcCol" type="com.sunopsis.sql.DbInt"><![CDATA[null]]></Field>
	<Field name="ITable" type="com.sunopsis.sql.DbInt"><![CDATA[1474]]></Field>
	<Field name="ITxtColDesc" type="com.sunopsis.sql.DbInt"><![CDATA[null]]></Field>
	<Field name="LastDate" type="java.sql.Timestamp"><![CDATA[2018-05-21 01:08:04.0]]></Field>
	<Field name="LastUser" type="java.lang.String"><![CDATA[SUPERVISOR]]></Field>
	<Field name="Longc" type="com.sunopsis.sql.DbInt"><![CDATA[3500]]></Field>
	<Field name="Pos" type="com.sunopsis.sql.DbInt"><![CDATA[2]]></Field>
	<Field name="RecCodeList" type="java.lang.String">null</Field>
	<Field name="Scalec" type="com.sunopsis.sql.DbInt"><![CDATA[null]]></Field>
	<Field name="ScdColType" type="java.lang.String">null</Field>
	<Field name="SourceDt" type="java.lang.String"><![CDATA[VARCHAR2]]></Field>
</Object>
<Object class="com.sunopsis.dwg.dbobj.SnpCol">
		<Field name="Bytes" type="com.sunopsis.sql.DbInt"><![CDATA[0]]></Field>
	<Field name="CheckFlow" type="java.lang.String"><![CDATA[1]]></Field>
	<Field name="CheckStat" type="java.lang.String"><![CDATA[0]]></Field>
	<Field name="ColDecSep" type="java.lang.String">null</Field>
	<Field name="ColFormat" type="java.lang.String">null</Field>
	<Field name="ColHeading" type="java.lang.String"><![CDATA[END_DATE]]></Field>
	<Field name="ColMandatory" type="java.lang.String"><![CDATA[0]]></Field>
	<Field name="ColName" type="java.lang.String"><![CDATA[END_DATE]]></Field>
	<Field name="ColNullIfErr" type="java.lang.String">null</Field>
	<Field name="DataFormat" type="java.lang.String">null</Field>
	<Field name="DefValue" type="java.lang.String">null</Field>
	<Field name="ExtVersion" type="java.lang.String">null</Field>
	<Field name="FilePos" type="com.sunopsis.sql.DbInt"><![CDATA[null]]></Field>
	<Field name="FirstDate" type="java.sql.Timestamp"><![CDATA[2018-05-20 00:30:51.0]]></Field>
	<Field name="FirstUser" type="java.lang.String"><![CDATA[SUPERVISOR]]></Field>
	<Field name="GlobalId" type="java.lang.String"><![CDATA[344c207e-ef6d-4937-b90c-fe0336469169]]></Field>
	<Field name="HbaseEncoding" type="java.lang.String">null</Field>
	<Field name="HiveSortbyPos" type="com.sunopsis.sql.DbInt"><![CDATA[null]]></Field>
	<Field name="IndChange" type="java.lang.String"><![CDATA[U]]></Field>
	<Field name="IndHiveCluster" type="java.lang.String">null</Field>
	<Field name="IndHivePartition" type="java.lang.String">null</Field>
	<Field name="IndHiveSort" type="java.lang.String">null</Field>
	<Field name="IndHiveSortbyAsc" type="java.lang.String">null</Field>
	<Field name="IndIn" type="java.lang.String">null</Field>
	<Field name="IndOut" type="java.lang.String">null</Field>
	<Field name="IndWrite" type="java.lang.String"><![CDATA[1]]></Field>
	<Field name="IndWsInsert" type="java.lang.String"><![CDATA[1]]></Field>
	<Field name="IndWsSelect" type="java.lang.String"><![CDATA[1]]></Field>
	<Field name="IndWsUpdate" type="java.lang.String"><![CDATA[1]]></Field>
	<Field name="IntVersion" type="com.sunopsis.sql.DbInt"><![CDATA[4]]></Field>
	<Field name="ICol" type="com.sunopsis.sql.DbInt"><![CDATA[13466]]></Field>
	<Field name="ISrcCol" type="com.sunopsis.sql.DbInt"><![CDATA[null]]></Field>
	<Field name="ITable" type="com.sunopsis.sql.DbInt"><![CDATA[1474]]></Field>
	<Field name="ITxtColDesc" type="com.sunopsis.sql.DbInt"><![CDATA[null]]></Field>
	<Field name="LastDate" type="java.sql.Timestamp"><![CDATA[2018-05-21 01:08:04.0]]></Field>
	<Field name="LastUser" type="java.lang.String"><![CDATA[SUPERVISOR]]></Field>
	<Field name="Longc" type="com.sunopsis.sql.DbInt"><![CDATA[6]]></Field>
	<Field name="Pos" type="com.sunopsis.sql.DbInt"><![CDATA[3]]></Field>
	<Field name="RecCodeList" type="java.lang.String">null</Field>
	<Field name="Scalec" type="com.sunopsis.sql.DbInt"><![CDATA[null]]></Field>
	<Field name="ScdColType" type="java.lang.String">null</Field>
	<Field name="SourceDt" type="java.lang.String"><![CDATA[TIMESTAMP]]></Field>
</Object>
<Object class="com.sunopsis.dwg.dbobj.SnpCol">
		<Field name="Bytes" type="com.sunopsis.sql.DbInt"><![CDATA[0]]></Field>
	<Field name="CheckFlow" type="java.lang.String"><![CDATA[1]]></Field>
	<Field name="CheckStat" type="java.lang.String"><![CDATA[0]]></Field>
	<Field name="ColDecSep" type="java.lang.String">null</Field>
	<Field name="ColFormat" type="java.lang.String">null</Field>
	<Field name="ColHeading" type="java.lang.String"><![CDATA[RESTRAINT_TYPE]]></Field>
	<Field name="ColMandatory" type="java.lang.String"><![CDATA[0]]></Field>
	<Field name="ColName" type="java.lang.String"><![CDATA[RESTRAINT_TYPE]]></Field>
	<Field name="ColNullIfErr" type="java.lang.String">null</Field>
	<Field name="DataFormat" type="java.lang.String">null</Field>
	<Field name="DefValue" type="java.lang.String">null</Field>
	<Field name="ExtVersion" type="java.lang.String">null</Field>
	<Field name="FilePos" type="com.sunopsis.sql.DbInt"><![CDATA[null]]></Field>
	<Field name="FirstDate" type="java.sql.Timestamp"><![CDATA[2018-05-20 00:30:51.0]]></Field>
	<Field name="FirstUser" type="java.lang.String"><![CDATA[SUPERVISOR]]></Field>
	<Field name="GlobalId" type="java.lang.String"><![CDATA[9c5bbcc9-7e58-4213-aec5-199d61f2f78d]]></Field>
	<Field name="HbaseEncoding" type="java.lang.String">null</Field>
	<Field name="HiveSortbyPos" type="com.sunopsis.sql.DbInt"><![CDATA[null]]></Field>
	<Field name="IndChange" type="java.lang.String"><![CDATA[U]]></Field>
	<Field name="IndHiveCluster" type="java.lang.String">null</Field>
	<Field name="IndHivePartition" type="java.lang.String">null</Field>
	<Field name="IndHiveSort" type="java.lang.String">null</Field>
	<Field name="IndHiveSortbyAsc" type="java.lang.String">null</Field>
	<Field name="IndIn" type="java.lang.String">null</Field>
	<Field name="IndOut" type="java.lang.String">null</Field>
	<Field name="IndWrite" type="java.lang.String"><![CDATA[1]]></Field>
	<Field name="IndWsInsert" type="java.lang.String"><![CDATA[1]]></Field>
	<Field name="IndWsSelect" type="java.lang.String"><![CDATA[1]]></Field>
	<Field name="IndWsUpdate" type="java.lang.String"><![CDATA[1]]></Field>
	<Field name="IntVersion" type="com.sunopsis.sql.DbInt"><![CDATA[4]]></Field>
	<Field name="ICol" type="com.sunopsis.sql.DbInt"><![CDATA[13467]]></Field>
	<Field name="ISrcCol" type="com.sunopsis.sql.DbInt"><![CDATA[null]]></Field>
	<Field name="ITable" type="com.sunopsis.sql.DbInt"><![CDATA[1474]]></Field>
	<Field name="ITxtColDesc" type="com.sunopsis.sql.DbInt"><![CDATA[null]]></Field>
	<Field name="LastDate" type="java.sql.Timestamp"><![CDATA[2018-05-21 01:08:04.0]]></Field>
	<Field name="LastUser" type="java.lang.String"><![CDATA[SUPERVISOR]]></Field>
	<Field name="Longc" type="com.sunopsis.sql.DbInt"><![CDATA[10]]></Field>
	<Field name="Pos" type="com.sunopsis.sql.DbInt"><![CDATA[4]]></Field>
	<Field name="RecCodeList" type="java.lang.String">null</Field>
	<Field name="Scalec" type="com.sunopsis.sql.DbInt"><![CDATA[0]]></Field>
	<Field name="ScdColType" type="java.lang.String">null</Field>
	<Field name="SourceDt" type="java.lang.String"><![CDATA[NUMBER]]></Field>
</Object>
<Object class="com.sunopsis.dwg.dbobj.SnpCol">
		<Field name="Bytes" type="com.sunopsis.sql.DbInt"><![CDATA[0]]></Field>
	<Field name="CheckFlow" type="java.lang.String"><![CDATA[1]]></Field>
	<Field name="CheckStat" type="java.lang.String"><![CDATA[0]]></Field>
	<Field name="ColDecSep" type="java.lang.String">null</Field>
	<Field name="ColFormat" type="java.lang.String">null</Field>
	<Field name="ColHeading" type="java.lang.String"><![CDATA[BEGIN_TIME_HOUR]]></Field>
	<Field name="ColMandatory" type="java.lang.String"><![CDATA[0]]></Field>
	<Field name="ColName" type="java.lang.String"><![CDATA[BEGIN_TIME_HOUR]]></Field>
	<Field name="ColNullIfErr" type="java.lang.String">null</Field>
	<Field name="DataFormat" type="java.lang.String">null</Field>
	<Field name="DefValue" type="java.lang.String">null</Field>
	<Field name="ExtVersion" type="java.lang.String">null</Field>
	<Field name="FilePos" type="com.sunopsis.sql.DbInt"><![CDATA[null]]></Field>
	<Field name="FirstDate" type="java.sql.Timestamp"><![CDATA[2018-05-20 00:30:51.0]]></Field>
	<Field name="FirstUser" type="java.lang.String"><![CDATA[SUPERVISOR]]></Field>
	<Field name="GlobalId" type="java.lang.String"><![CDATA[d9524ff2-1b03-4479-a726-6eecf55250f9]]></Field>
	<Field name="HbaseEncoding" type="java.lang.String">null</Field>
	<Field name="HiveSortbyPos" type="com.sunopsis.sql.DbInt"><![CDATA[null]]></Field>
	<Field name="IndChange" type="java.lang.String"><![CDATA[U]]></Field>
	<Field name="IndHiveCluster" type="java.lang.String">null</Field>
	<Field name="IndHivePartition" type="java.lang.String">null</Field>
	<Field name="IndHiveSort" type="java.lang.String">null</Field>
	<Field name="IndHiveSortbyAsc" type="java.lang.String">null</Field>
	<Field name="IndIn" type="java.lang.String">null</Field>
	<Field name="IndOut" type="java.lang.String">null</Field>
	<Field name="IndWrite" type="java.lang.String"><![CDATA[1]]></Field>
	<Field name="IndWsInsert" type="java.lang.String"><![CDATA[1]]></Field>
	<Field name="IndWsSelect" type="java.lang.String"><![CDATA[1]]></Field>
	<Field name="IndWsUpdate" type="java.lang.String"><![CDATA[1]]></Field>
	<Field name="IntVersion" type="com.sunopsis.sql.DbInt"><![CDATA[4]]></Field>
	<Field name="ICol" type="com.sunopsis.sql.DbInt"><![CDATA[13468]]></Field>
	<Field name="ISrcCol" type="com.sunopsis.sql.DbInt"><![CDATA[null]]></Field>
	<Field name="ITable" type="com.sunopsis.sql.DbInt"><![CDATA[1474]]></Field>
	<Field name="ITxtColDesc" type="com.sunopsis.sql.DbInt"><![CDATA[null]]></Field>
	<Field name="LastDate" type="java.sql.Timestamp"><![CDATA[2018-05-21 01:08:04.0]]></Field>
	<Field name="LastUser" type="java.lang.String"><![CDATA[SUPERVISOR]]></Field>
	<Field name="Longc" type="com.sunopsis.sql.DbInt"><![CDATA[255]]></Field>
	<Field name="Pos" type="com.sunopsis.sql.DbInt"><![CDATA[5]]></Field>
	<Field name="RecCodeList" type="java.lang.String">null</Field>
	<Field name="Scalec" type="com.sunopsis.sql.DbInt"><![CDATA[null]]></Field>
	<Field name="ScdColType" type="java.lang.String">null</Field>
	<Field name="SourceDt" type="java.lang.String"><![CDATA[VARCHAR2]]></Field>
</Object>
<Object class="com.sunopsis.dwg.dbobj.SnpCol">
		<Field name="Bytes" type="com.sunopsis.sql.DbInt"><![CDATA[0]]></Field>
	<Field name="CheckFlow" type="java.lang.String"><![CDATA[1]]></Field>
	<Field name="CheckStat" type="java.lang.String"><![CDATA[0]]></Field>
	<Field name="ColDecSep" type="java.lang.String">null</Field>
	<Field name="ColFormat" type="java.lang.String">null</Field>
	<Field name="ColHeading" type="java.lang.String"><![CDATA[BEGIN_TIME_MIN]]></Field>
	<Field name="ColMandatory" type="java.lang.String"><![CDATA[0]]></Field>
	<Field name="ColName" type="java.lang.String"><![CDATA[BEGIN_TIME_MIN]]></Field>
	<Field name="ColNullIfErr" type="java.lang.String">null</Field>
	<Field name="DataFormat" type="java.lang.String">null</Field>
	<Field name="DefValue" type="java.lang.String">null</Field>
	<Field name="ExtVersion" type="java.lang.String">null</Field>
	<Field name="FilePos" type="com.sunopsis.sql.DbInt"><![CDATA[null]]></Field>
	<Field name="FirstDate" type="java.sql.Timestamp"><![CDATA[2018-05-20 00:30:51.0]]></Field>
	<Field name="FirstUser" type="java.lang.String"><![CDATA[SUPERVISOR]]></Field>
	<Field name="GlobalId" type="java.lang.String"><![CDATA[21857481-8b1c-4c13-8ecb-130a5b562536]]></Field>
	<Field name="HbaseEncoding" type="java.lang.String">null</Field>
	<Field name="HiveSortbyPos" type="com.sunopsis.sql.DbInt"><![CDATA[null]]></Field>
	<Field name="IndChange" type="java.lang.String"><![CDATA[U]]></Field>
	<Field name="IndHiveCluster" type="java.lang.String">null</Field>
	<Field name="IndHivePartition" type="java.lang.String">null</Field>
	<Field name="IndHiveSort" type="java.lang.String">null</Field>
	<Field name="IndHiveSortbyAsc" type="java.lang.String">null</Field>
	<Field name="IndIn" type="java.lang.String">null</Field>
	<Field name="IndOut" type="java.lang.String">null</Field>
	<Field name="IndWrite" type="java.lang.String"><![CDATA[1]]></Field>
	<Field name="IndWsInsert" type="java.lang.String"><![CDATA[1]]></Field>
	<Field name="IndWsSelect" type="java.lang.String"><![CDATA[1]]></Field>
	<Field name="IndWsUpdate" type="java.lang.String"><![CDATA[1]]></Field>
	<Field name="IntVersion" type="com.sunopsis.sql.DbInt"><![CDATA[4]]></Field>
	<Field name="ICol" type="com.sunopsis.sql.DbInt"><![CDATA[13469]]></Field>
	<Field name="ISrcCol" type="com.sunopsis.sql.DbInt"><![CDATA[null]]></Field>
	<Field name="ITable" type="com.sunopsis.sql.DbInt"><![CDATA[1474]]></Field>
	<Field name="ITxtColDesc" type="com.sunopsis.sql.DbInt"><![CDATA[null]]></Field>
	<Field name="LastDate" type="java.sql.Timestamp"><![CDATA[2018-05-21 01:08:04.0]]></Field>
	<Field name="LastUser" type="java.lang.String"><![CDATA[SUPERVISOR]]></Field>
	<Field name="Longc" type="com.sunopsis.sql.DbInt"><![CDATA[255]]></Field>
	<Field name="Pos" type="com.sunopsis.sql.DbInt"><![CDATA[6]]></Field>
	<Field name="RecCodeList" type="java.lang.String">null</Field>
	<Field name="Scalec" type="com.sunopsis.sql.DbInt"><![CDATA[null]]></Field>
	<Field name="ScdColType" type="java.lang.String">null</Field>
	<Field name="SourceDt" type="java.lang.String"><![CDATA[VARCHAR2]]></Field>
</Object>
<Object class="com.sunopsis.dwg.dbobj.SnpCol">
		<Field name="Bytes" type="com.sunopsis.sql.DbInt"><![CDATA[0]]></Field>
	<Field name="CheckFlow" type="java.lang.String"><![CDATA[1]]></Field>
	<Field name="CheckStat" type="java.lang.String"><![CDATA[0]]></Field>
	<Field name="ColDecSep" type="java.lang.String">null</Field>
	<Field name="ColFormat" type="java.lang.String">null</Field>
	<Field name="ColHeading" type="java.lang.String"><![CDATA[BEGIN_TIME_AM_PM]]></Field>
	<Field name="ColMandatory" type="java.lang.String"><![CDATA[0]]></Field>
	<Field name="ColName" type="java.lang.String"><![CDATA[BEGIN_TIME_AM_PM]]></Field>
	<Field name="ColNullIfErr" type="java.lang.String">null</Field>
	<Field name="DataFormat" type="java.lang.String">null</Field>
	<Field name="DefValue" type="java.lang.String">null</Field>
	<Field name="ExtVersion" type="java.lang.String">null</Field>
	<Field name="FilePos" type="com.sunopsis.sql.DbInt"><![CDATA[null]]></Field>
	<Field name="FirstDate" type="java.sql.Timestamp"><![CDATA[2018-05-20 00:30:51.0]]></Field>
	<Field name="FirstUser" type="java.lang.String"><![CDATA[SUPERVISOR]]></Field>
	<Field name="GlobalId" type="java.lang.String"><![CDATA[b17320c0-975e-4c1f-ba98-b3bf1c6c8241]]></Field>
	<Field name="HbaseEncoding" type="java.lang.String">null</Field>
	<Field name="HiveSortbyPos" type="com.sunopsis.sql.DbInt"><![CDATA[null]]></Field>
	<Field name="IndChange" type="java.lang.String"><![CDATA[U]]></Field>
	<Field name="IndHiveCluster" type="java.lang.String">null</Field>
	<Field name="IndHivePartition" type="java.lang.String">null</Field>
	<Field name="IndHiveSort" type="java.lang.String">null</Field>
	<Field name="IndHiveSortbyAsc" type="java.lang.String">null</Field>
	<Field name="IndIn" type="java.lang.String">null</Field>
	<Field name="IndOut" type="java.lang.String">null</Field>
	<Field name="IndWrite" type="java.lang.String"><![CDATA[1]]></Field>
	<Field name="IndWsInsert" type="java.lang.String"><![CDATA[1]]></Field>
	<Field name="IndWsSelect" type="java.lang.String"><![CDATA[1]]></Field>
	<Field name="IndWsUpdate" type="java.lang.String"><![CDATA[1]]></Field>
	<Field name="IntVersion" type="com.sunopsis.sql.DbInt"><![CDATA[4]]></Field>
	<Field name="ICol" type="com.sunopsis.sql.DbInt"><![CDATA[13470]]></Field>
	<Field name="ISrcCol" type="com.sunopsis.sql.DbInt"><![CDATA[null]]></Field>
	<Field name="ITable" type="com.sunopsis.sql.DbInt"><![CDATA[1474]]></Field>
	<Field name="ITxtColDesc" type="com.sunopsis.sql.DbInt"><![CDATA[null]]></Field>
	<Field name="LastDate" type="java.sql.Timestamp"><![CDATA[2018-05-21 01:08:04.0]]></Field>
	<Field name="LastUser" type="java.lang.String"><![CDATA[SUPERVISOR]]></Field>
	<Field name="Longc" type="com.sunopsis.sql.DbInt"><![CDATA[255]]></Field>
	<Field name="Pos" type="com.sunopsis.sql.DbInt"><![CDATA[7]]></Field>
	<Field name="RecCodeList" type="java.lang.String">null</Field>
	<Field name="Scalec" type="com.sunopsis.sql.DbInt"><![CDATA[null]]></Field>
	<Field name="ScdColType" type="java.lang.String">null</Field>
	<Field name="SourceDt" type="java.lang.String"><![CDATA[VARCHAR2]]></Field>
</Object>
<Object class="com.sunopsis.dwg.dbobj.SnpCol">
		<Field name="Bytes" type="com.sunopsis.sql.DbInt"><![CDATA[0]]></Field>
	<Field name="CheckFlow" type="java.lang.String"><![CDATA[1]]></Field>
	<Field name="CheckStat" type="java.lang.String"><![CDATA[0]]></Field>
	<Field name="ColDecSep" type="java.lang.String">null</Field>
	<Field name="ColFormat" type="java.lang.String">null</Field>
	<Field name="ColHeading" type="java.lang.String"><![CDATA[END_TIME_HOUR]]></Field>
	<Field name="ColMandatory" type="java.lang.String"><![CDATA[0]]></Field>
	<Field name="ColName" type="java.lang.String"><![CDATA[END_TIME_HOUR]]></Field>
	<Field name="ColNullIfErr" type="java.lang.String">null</Field>
	<Field name="DataFormat" type="java.lang.String">null</Field>
	<Field name="DefValue" type="java.lang.String">null</Field>
	<Field name="ExtVersion" type="java.lang.String">null</Field>
	<Field name="FilePos" type="com.sunopsis.sql.DbInt"><![CDATA[null]]></Field>
	<Field name="FirstDate" type="java.sql.Timestamp"><![CDATA[2018-05-20 00:30:51.0]]></Field>
	<Field name="FirstUser" type="java.lang.String"><![CDATA[SUPERVISOR]]></Field>
	<Field name="GlobalId" type="java.lang.String"><![CDATA[654bc2b6-ceca-4c5f-a759-fe1b8af186da]]></Field>
	<Field name="HbaseEncoding" type="java.lang.String">null</Field>
	<Field name="HiveSortbyPos" type="com.sunopsis.sql.DbInt"><![CDATA[null]]></Field>
	<Field name="IndChange" type="java.lang.String"><![CDATA[U]]></Field>
	<Field name="IndHiveCluster" type="java.lang.String">null</Field>
	<Field name="IndHivePartition" type="java.lang.String">null</Field>
	<Field name="IndHiveSort" type="java.lang.String">null</Field>
	<Field name="IndHiveSortbyAsc" type="java.lang.String">null</Field>
	<Field name="IndIn" type="java.lang.String">null</Field>
	<Field name="IndOut" type="java.lang.String">null</Field>
	<Field name="IndWrite" type="java.lang.String"><![CDATA[1]]></Field>
	<Field name="IndWsInsert" type="java.lang.String"><![CDATA[1]]></Field>
	<Field name="IndWsSelect" type="java.lang.String"><![CDATA[1]]></Field>
	<Field name="IndWsUpdate" type="java.lang.String"><![CDATA[1]]></Field>
	<Field name="IntVersion" type="com.sunopsis.sql.DbInt"><![CDATA[4]]></Field>
	<Field name="ICol" type="com.sunopsis.sql.DbInt"><![CDATA[13471]]></Field>
	<Field name="ISrcCol" type="com.sunopsis.sql.DbInt"><![CDATA[null]]></Field>
	<Field name="ITable" type="com.sunopsis.sql.DbInt"><![CDATA[1474]]></Field>
	<Field name="ITxtColDesc" type="com.sunopsis.sql.DbInt"><![CDATA[null]]></Field>
	<Field name="LastDate" type="java.sql.Timestamp"><![CDATA[2018-05-21 01:08:04.0]]></Field>
	<Field name="LastUser" type="java.lang.String"><![CDATA[SUPERVISOR]]></Field>
	<Field name="Longc" type="com.sunopsis.sql.DbInt"><![CDATA[255]]></Field>
	<Field name="Pos" type="com.sunopsis.sql.DbInt"><![CDATA[8]]></Field>
	<Field name="RecCodeList" type="java.lang.String">null</Field>
	<Field name="Scalec" type="com.sunopsis.sql.DbInt"><![CDATA[null]]></Field>
	<Field name="ScdColType" type="java.lang.String">null</Field>
	<Field name="SourceDt" type="java.lang.String"><![CDATA[VARCHAR2]]></Field>
</Object>
<Object class="com.sunopsis.dwg.dbobj.SnpCol">
		<Field name="Bytes" type="com.sunopsis.sql.DbInt"><![CDATA[0]]></Field>
	<Field name="CheckFlow" type="java.lang.String"><![CDATA[1]]></Field>
	<Field name="CheckStat" type="java.lang.String"><![CDATA[0]]></Field>
	<Field name="ColDecSep" type="java.lang.String">null</Field>
	<Field name="ColFormat" type="java.lang.String">null</Field>
	<Field name="ColHeading" type="java.lang.String"><![CDATA[END_TIME_MIN]]></Field>
	<Field name="ColMandatory" type="java.lang.String"><![CDATA[0]]></Field>
	<Field name="ColName" type="java.lang.String"><![CDATA[END_TIME_MIN]]></Field>
	<Field name="ColNullIfErr" type="java.lang.String">null</Field>
	<Field name="DataFormat" type="java.lang.String">null</Field>
	<Field name="DefValue" type="java.lang.String">null</Field>
	<Field name="ExtVersion" type="java.lang.String">null</Field>
	<Field name="FilePos" type="com.sunopsis.sql.DbInt"><![CDATA[null]]></Field>
	<Field name="FirstDate" type="java.sql.Timestamp"><![CDATA[2018-05-20 00:30:51.0]]></Field>
	<Field name="FirstUser" type="java.lang.String"><![CDATA[SUPERVISOR]]></Field>
	<Field name="GlobalId" type="java.lang.String"><![CDATA[e42629bd-c0b3-40f8-b9c5-9a0246efb225]]></Field>
	<Field name="HbaseEncoding" type="java.lang.String">null</Field>
	<Field name="HiveSortbyPos" type="com.sunopsis.sql.DbInt"><![CDATA[null]]></Field>
	<Field name="IndChange" type="java.lang.String"><![CDATA[U]]></Field>
	<Field name="IndHiveCluster" type="java.lang.String">null</Field>
	<Field name="IndHivePartition" type="java.lang.String">null</Field>
	<Field name="IndHiveSort" type="java.lang.String">null</Field>
	<Field name="IndHiveSortbyAsc" type="java.lang.String">null</Field>
	<Field name="IndIn" type="java.lang.String">null</Field>
	<Field name="IndOut" type="java.lang.String">null</Field>
	<Field name="IndWrite" type="java.lang.String"><![CDATA[1]]></Field>
	<Field name="IndWsInsert" type="java.lang.String"><![CDATA[1]]></Field>
	<Field name="IndWsSelect" type="java.lang.String"><![CDATA[1]]></Field>
	<Field name="IndWsUpdate" type="java.lang.String"><![CDATA[1]]></Field>
	<Field name="IntVersion" type="com.sunopsis.sql.DbInt"><![CDATA[4]]></Field>
	<Field name="ICol" type="com.sunopsis.sql.DbInt"><![CDATA[13472]]></Field>
	<Field name="ISrcCol" type="com.sunopsis.sql.DbInt"><![CDATA[null]]></Field>
	<Field name="ITable" type="com.sunopsis.sql.DbInt"><![CDATA[1474]]></Field>
	<Field name="ITxtColDesc" type="com.sunopsis.sql.DbInt"><![CDATA[null]]></Field>
	<Field name="LastDate" type="java.sql.Timestamp"><![CDATA[2018-05-21 01:08:04.0]]></Field>
	<Field name="LastUser" type="java.lang.String"><![CDATA[SUPERVISOR]]></Field>
	<Field name="Longc" type="com.sunopsis.sql.DbInt"><![CDATA[255]]></Field>
	<Field name="Pos" type="com.sunopsis.sql.DbInt"><![CDATA[9]]></Field>
	<Field name="RecCodeList" type="java.lang.String">null</Field>
	<Field name="Scalec" type="com.sunopsis.sql.DbInt"><![CDATA[null]]></Field>
	<Field name="ScdColType" type="java.lang.String">null</Field>
	<Field name="SourceDt" type="java.lang.String"><![CDATA[VARCHAR2]]></Field>
</Object>
<Object class="com.sunopsis.dwg.dbobj.SnpCol">
		<Field name="Bytes" type="com.sunopsis.sql.DbInt"><![CDATA[0]]></Field>
	<Field name="CheckFlow" type="java.lang.String"><![CDATA[1]]></Field>
	<Field name="CheckStat" type="java.lang.String"><![CDATA[0]]></Field>
	<Field name="ColDecSep" type="java.lang.String">null</Field>
	<Field name="ColFormat" type="java.lang.String">null</Field>
	<Field name="ColHeading" type="java.lang.String"><![CDATA[END_TIME_AM_PM]]></Field>
	<Field name="ColMandatory" type="java.lang.String"><![CDATA[0]]></Field>
	<Field name="ColName" type="java.lang.String"><![CDATA[END_TIME_AM_PM]]></Field>
	<Field name="ColNullIfErr" type="java.lang.String">null</Field>
	<Field name="DataFormat" type="java.lang.String">null</Field>
	<Field name="DefValue" type="java.lang.String">null</Field>
	<Field name="ExtVersion" type="java.lang.String">null</Field>
	<Field name="FilePos" type="com.sunopsis.sql.DbInt"><![CDATA[null]]></Field>
	<Field name="FirstDate" type="java.sql.Timestamp"><![CDATA[2018-05-20 00:30:51.0]]></Field>
	<Field name="FirstUser" type="java.lang.String"><![CDATA[SUPERVISOR]]></Field>
	<Field name="GlobalId" type="java.lang.String"><![CDATA[506bde4a-5e0b-4cca-a11e-64e24bb2c9b1]]></Field>
	<Field name="HbaseEncoding" type="java.lang.String">null</Field>
	<Field name="HiveSortbyPos" type="com.sunopsis.sql.DbInt"><![CDATA[null]]></Field>
	<Field name="IndChange" type="java.lang.String"><![CDATA[U]]></Field>
	<Field name="IndHiveCluster" type="java.lang.String">null</Field>
	<Field name="IndHivePartition" type="java.lang.String">null</Field>
	<Field name="IndHiveSort" type="java.lang.String">null</Field>
	<Field name="IndHiveSortbyAsc" type="java.lang.String">null</Field>
	<Field name="IndIn" type="java.lang.String">null</Field>
	<Field name="IndOut" type="java.lang.String">null</Field>
	<Field name="IndWrite" type="java.lang.String"><![CDATA[1]]></Field>
	<Field name="IndWsInsert" type="java.lang.String"><![CDATA[1]]></Field>
	<Field name="IndWsSelect" type="java.lang.String"><![CDATA[1]]></Field>
	<Field name="IndWsUpdate" type="java.lang.String"><![CDATA[1]]></Field>
	<Field name="IntVersion" type="com.sunopsis.sql.DbInt"><![CDATA[4]]></Field>
	<Field name="ICol" type="com.sunopsis.sql.DbInt"><![CDATA[13473]]></Field>
	<Field name="ISrcCol" type="com.sunopsis.sql.DbInt"><![CDATA[null]]></Field>
	<Field name="ITable" type="com.sunopsis.sql.DbInt"><![CDATA[1474]]></Field>
	<Field name="ITxtColDesc" type="com.sunopsis.sql.DbInt"><![CDATA[null]]></Field>
	<Field name="LastDate" type="java.sql.Timestamp"><![CDATA[2018-05-21 01:08:04.0]]></Field>
	<Field name="LastUser" type="java.lang.String"><![CDATA[SUPERVISOR]]></Field>
	<Field name="Longc" type="com.sunopsis.sql.DbInt"><![CDATA[255]]></Field>
	<Field name="Pos" type="com.sunopsis.sql.DbInt"><![CDATA[10]]></Field>
	<Field name="RecCodeList" type="java.lang.String">null</Field>
	<Field name="Scalec" type="com.sunopsis.sql.DbInt"><![CDATA[null]]></Field>
	<Field name="ScdColType" type="java.lang.String">null</Field>
	<Field name="SourceDt" type="java.lang.String"><![CDATA[VARCHAR2]]></Field>
</Object>
<Object class="com.sunopsis.dwg.dbobj.SnpCol">
		<Field name="Bytes" type="com.sunopsis.sql.DbInt"><![CDATA[0]]></Field>
	<Field name="CheckFlow" type="java.lang.String"><![CDATA[1]]></Field>
	<Field name="CheckStat" type="java.lang.String"><![CDATA[0]]></Field>
	<Field name="ColDecSep" type="java.lang.String">null</Field>
	<Field name="ColFormat" type="java.lang.String">null</Field>
	<Field name="ColHeading" type="java.lang.String"><![CDATA[LOCATION_OTHER]]></Field>
	<Field name="ColMandatory" type="java.lang.String"><![CDATA[0]]></Field>
	<Field name="ColName" type="java.lang.String"><![CDATA[LOCATION_OTHER]]></Field>
	<Field name="ColNullIfErr" type="java.lang.String">null</Field>
	<Field name="DataFormat" type="java.lang.String">null</Field>
	<Field name="DefValue" type="java.lang.String">null</Field>
	<Field name="ExtVersion" type="java.lang.String">null</Field>
	<Field name="FilePos" type="com.sunopsis.sql.DbInt"><![CDATA[null]]></Field>
	<Field name="FirstDate" type="java.sql.Timestamp"><![CDATA[2018-05-20 00:30:51.0]]></Field>
	<Field name="FirstUser" type="java.lang.String"><![CDATA[SUPERVISOR]]></Field>
	<Field name="GlobalId" type="java.lang.String"><![CDATA[e1e4fd90-830f-42f4-902c-2ba92518850c]]></Field>
	<Field name="HbaseEncoding" type="java.lang.String">null</Field>
	<Field name="HiveSortbyPos" type="com.sunopsis.sql.DbInt"><![CDATA[null]]></Field>
	<Field name="IndChange" type="java.lang.String"><![CDATA[U]]></Field>
	<Field name="IndHiveCluster" type="java.lang.String">null</Field>
	<Field name="IndHivePartition" type="java.lang.String">null</Field>
	<Field name="IndHiveSort" type="java.lang.String">null</Field>
	<Field name="IndHiveSortbyAsc" type="java.lang.String">null</Field>
	<Field name="IndIn" type="java.lang.String">null</Field>
	<Field name="IndOut" type="java.lang.String">null</Field>
	<Field name="IndWrite" type="java.lang.String"><![CDATA[1]]></Field>
	<Field name="IndWsInsert" type="java.lang.String"><![CDATA[1]]></Field>
	<Field name="IndWsSelect" type="java.lang.String"><![CDATA[1]]></Field>
	<Field name="IndWsUpdate" type="java.lang.String"><![CDATA[1]]></Field>
	<Field name="IntVersion" type="com.sunopsis.sql.DbInt"><![CDATA[4]]></Field>
	<Field name="ICol" type="com.sunopsis.sql.DbInt"><![CDATA[13474]]></Field>
	<Field name="ISrcCol" type="com.sunopsis.sql.DbInt"><![CDATA[null]]></Field>
	<Field name="ITable" type="com.sunopsis.sql.DbInt"><![CDATA[1474]]></Field>
	<Field name="ITxtColDesc" type="com.sunopsis.sql.DbInt"><![CDATA[null]]></Field>
	<Field name="LastDate" type="java.sql.Timestamp"><![CDATA[2018-05-21 01:08:04.0]]></Field>
	<Field name="LastUser" type="java.lang.String"><![CDATA[SUPERVISOR]]></Field>
	<Field name="Longc" type="com.sunopsis.sql.DbInt"><![CDATA[64]]></Field>
	<Field name="Pos" type="com.sunopsis.sql.DbInt"><![CDATA[11]]></Field>
	<Field name="RecCodeList" type="java.lang.String">null</Field>
	<Field name="Scalec" type="com.sunopsis.sql.DbInt"><![CDATA[null]]></Field>
	<Field name="ScdColType" type="java.lang.String">null</Field>
	<Field name="SourceDt" type="java.lang.String"><![CDATA[VARCHAR2]]></Field>
</Object>
<Object class="com.sunopsis.dwg.dbobj.SnpCol">
		<Field name="Bytes" type="com.sunopsis.sql.DbInt"><![CDATA[0]]></Field>
	<Field name="CheckFlow" type="java.lang.String"><![CDATA[1]]></Field>
	<Field name="CheckStat" type="java.lang.String"><![CDATA[0]]></Field>
	<Field name="ColDecSep" type="java.lang.String">null</Field>
	<Field name="ColFormat" type="java.lang.String">null</Field>
	<Field name="ColHeading" type="java.lang.String"><![CDATA[RESTRAINT_TYPE_OTHER]]></Field>
	<Field name="ColMandatory" type="java.lang.String"><![CDATA[0]]></Field>
	<Field name="ColName" type="java.lang.String"><![CDATA[RESTRAINT_TYPE_OTHER]]></Field>
	<Field name="ColNullIfErr" type="java.lang.String">null</Field>
	<Field name="DataFormat" type="java.lang.String">null</Field>
	<Field name="DefValue" type="java.lang.String">null</Field>
	<Field name="ExtVersion" type="java.lang.String">null</Field>
	<Field name="FilePos" type="com.sunopsis.sql.DbInt"><![CDATA[null]]></Field>
	<Field name="FirstDate" type="java.sql.Timestamp"><![CDATA[2018-05-20 00:30:51.0]]></Field>
	<Field name="FirstUser" type="java.lang.String"><![CDATA[SUPERVISOR]]></Field>
	<Field name="GlobalId" type="java.lang.String"><![CDATA[e642172a-534a-4723-a21a-27b7ca06ac35]]></Field>
	<Field name="HbaseEncoding" type="java.lang.String">null</Field>
	<Field name="HiveSortbyPos" type="com.sunopsis.sql.DbInt"><![CDATA[null]]></Field>
	<Field name="IndChange" type="java.lang.String"><![CDATA[U]]></Field>
	<Field name="IndHiveCluster" type="java.lang.String">null</Field>
	<Field name="IndHivePartition" type="java.lang.String">null</Field>
	<Field name="IndHiveSort" type="java.lang.String">null</Field>
	<Field name="IndHiveSortbyAsc" type="java.lang.String">null</Field>
	<Field name="IndIn" type="java.lang.String">null</Field>
	<Field name="IndOut" type="java.lang.String">null</Field>
	<Field name="IndWrite" type="java.lang.String"><![CDATA[1]]></Field>
	<Field name="IndWsInsert" type="java.lang.String"><![CDATA[1]]></Field>
	<Field name="IndWsSelect" type="java.lang.String"><![CDATA[1]]></Field>
	<Field name="IndWsUpdate" type="java.lang.String"><![CDATA[1]]></Field>
	<Field name="IntVersion" type="com.sunopsis.sql.DbInt"><![CDATA[4]]></Field>
	<Field name="ICol" type="com.sunopsis.sql.DbInt"><![CDATA[13475]]></Field>
	<Field name="ISrcCol" type="com.sunopsis.sql.DbInt"><![CDATA[null]]></Field>
	<Field name="ITable" type="com.sunopsis.sql.DbInt"><![CDATA[1474]]></Field>
	<Field name="ITxtColDesc" type="com.sunopsis.sql.DbInt"><![CDATA[null]]></Field>
	<Field name="LastDate" type="java.sql.Timestamp"><![CDATA[2018-05-21 01:08:04.0]]></Field>
	<Field name="LastUser" type="java.lang.String"><![CDATA[SUPERVISOR]]></Field>
	<Field name="Longc" type="com.sunopsis.sql.DbInt"><![CDATA[255]]></Field>
	<Field name="Pos" type="com.sunopsis.sql.DbInt"><![CDATA[12]]></Field>
	<Field name="RecCodeList" type="java.lang.String">null</Field>
	<Field name="Scalec" type="com.sunopsis.sql.DbInt"><![CDATA[null]]></Field>
	<Field name="ScdColType" type="java.lang.String">null</Field>
	<Field name="SourceDt" type="java.lang.String"><![CDATA[VARCHAR2]]></Field>
</Object>
<Object class="com.sunopsis.dwg.dbobj.SnpCol">
		<Field name="Bytes" type="com.sunopsis.sql.DbInt"><![CDATA[0]]></Field>
	<Field name="CheckFlow" type="java.lang.String"><![CDATA[1]]></Field>
	<Field name="CheckStat" type="java.lang.String"><![CDATA[0]]></Field>
	<Field name="ColDecSep" type="java.lang.String">null</Field>
	<Field name="ColFormat" type="java.lang.String">null</Field>
	<Field name="ColHeading" type="java.lang.String"><![CDATA[MEDICATION_NAME]]></Field>
	<Field name="ColMandatory" type="java.lang.String"><![CDATA[0]]></Field>
	<Field name="ColName" type="java.lang.String"><![CDATA[MEDICATION_NAME]]></Field>
	<Field name="ColNullIfErr" type="java.lang.String">null</Field>
	<Field name="DataFormat" type="java.lang.String">null</Field>
	<Field name="DefValue" type="java.lang.String">null</Field>
	<Field name="ExtVersion" type="java.lang.String">null</Field>
	<Field name="FilePos" type="com.sunopsis.sql.DbInt"><![CDATA[null]]></Field>
	<Field name="FirstDate" type="java.sql.Timestamp"><![CDATA[2018-05-20 00:30:51.0]]></Field>
	<Field name="FirstUser" type="java.lang.String"><![CDATA[SUPERVISOR]]></Field>
	<Field name="GlobalId" type="java.lang.String"><![CDATA[2d52c250-ae4e-4f0a-915b-e20bc6019522]]></Field>
	<Field name="HbaseEncoding" type="java.lang.String">null</Field>
	<Field name="HiveSortbyPos" type="com.sunopsis.sql.DbInt"><![CDATA[null]]></Field>
	<Field name="IndChange" type="java.lang.String"><![CDATA[U]]></Field>
	<Field name="IndHiveCluster" type="java.lang.String">null</Field>
	<Field name="IndHivePartition" type="java.lang.String">null</Field>
	<Field name="IndHiveSort" type="java.lang.String">null</Field>
	<Field name="IndHiveSortbyAsc" type="java.lang.String">null</Field>
	<Field name="IndIn" type="java.lang.String">null</Field>
	<Field name="IndOut" type="java.lang.String">null</Field>
	<Field name="IndWrite" type="java.lang.String"><![CDATA[1]]></Field>
	<Field name="IndWsInsert" type="java.lang.String"><![CDATA[1]]></Field>
	<Field name="IndWsSelect" type="java.lang.String"><![CDATA[1]]></Field>
	<Field name="IndWsUpdate" type="java.lang.String"><![CDATA[1]]></Field>
	<Field name="IntVersion" type="com.sunopsis.sql.DbInt"><![CDATA[4]]></Field>
	<Field name="ICol" type="com.sunopsis.sql.DbInt"><![CDATA[13476]]></Field>
	<Field name="ISrcCol" type="com.sunopsis.sql.DbInt"><![CDATA[null]]></Field>
	<Field name="ITable" type="com.sunopsis.sql.DbInt"><![CDATA[1474]]></Field>
	<Field name="ITxtColDesc" type="com.sunopsis.sql.DbInt"><![CDATA[null]]></Field>
	<Field name="LastDate" type="java.sql.Timestamp"><![CDATA[2018-05-21 01:08:04.0]]></Field>
	<Field name="LastUser" type="java.lang.String"><![CDATA[SUPERVISOR]]></Field>
	<Field name="Longc" type="com.sunopsis.sql.DbInt"><![CDATA[255]]></Field>
	<Field name="Pos" type="com.sunopsis.sql.DbInt"><![CDATA[13]]></Field>
	<Field name="RecCodeList" type="java.lang.String">null</Field>
	<Field name="Scalec" type="com.sunopsis.sql.DbInt"><![CDATA[null]]></Field>
	<Field name="ScdColType" type="java.lang.String">null</Field>
	<Field name="SourceDt" type="java.lang.String"><![CDATA[VARCHAR2]]></Field>
</Object>
<Object class="com.sunopsis.dwg.dbobj.SnpCol">
		<Field name="Bytes" type="com.sunopsis.sql.DbInt"><![CDATA[0]]></Field>
	<Field name="CheckFlow" type="java.lang.String"><![CDATA[1]]></Field>
	<Field name="CheckStat" type="java.lang.String"><![CDATA[0]]></Field>
	<Field name="ColDecSep" type="java.lang.String">null</Field>
	<Field name="ColFormat" type="java.lang.String">null</Field>
	<Field name="ColHeading" type="java.lang.String"><![CDATA[DOSAGE]]></Field>
	<Field name="ColMandatory" type="java.lang.String"><![CDATA[0]]></Field>
	<Field name="ColName" type="java.lang.String"><![CDATA[DOSAGE]]></Field>
	<Field name="ColNullIfErr" type="java.lang.String">null</Field>
	<Field name="DataFormat" type="java.lang.String">null</Field>
	<Field name="DefValue" type="java.lang.String">null</Field>
	<Field name="ExtVersion" type="java.lang.String">null</Field>
	<Field name="FilePos" type="com.sunopsis.sql.DbInt"><![CDATA[null]]></Field>
	<Field name="FirstDate" type="java.sql.Timestamp"><![CDATA[2018-05-20 00:30:51.0]]></Field>
	<Field name="FirstUser" type="java.lang.String"><![CDATA[SUPERVISOR]]></Field>
	<Field name="GlobalId" type="java.lang.String"><![CDATA[a7026339-984d-4b50-98e5-4c1f47631a75]]></Field>
	<Field name="HbaseEncoding" type="java.lang.String">null</Field>
	<Field name="HiveSortbyPos" type="com.sunopsis.sql.DbInt"><![CDATA[null]]></Field>
	<Field name="IndChange" type="java.lang.String"><![CDATA[U]]></Field>
	<Field name="IndHiveCluster" type="java.lang.String">null</Field>
	<Field name="IndHivePartition" type="java.lang.String">null</Field>
	<Field name="IndHiveSort" type="java.lang.String">null</Field>
	<Field name="IndHiveSortbyAsc" type="java.lang.String">null</Field>
	<Field name="IndIn" type="java.lang.String">null</Field>
	<Field name="IndOut" type="java.lang.String">null</Field>
	<Field name="IndWrite" type="java.lang.String"><![CDATA[1]]></Field>
	<Field name="IndWsInsert" type="java.lang.String"><![CDATA[1]]></Field>
	<Field name="IndWsSelect" type="java.lang.String"><![CDATA[1]]></Field>
	<Field name="IndWsUpdate" type="java.lang.String"><![CDATA[1]]></Field>
	<Field name="IntVersion" type="com.sunopsis.sql.DbInt"><![CDATA[4]]></Field>
	<Field name="ICol" type="com.sunopsis.sql.DbInt"><![CDATA[13477]]></Field>
	<Field name="ISrcCol" type="com.sunopsis.sql.DbInt"><![CDATA[null]]></Field>
	<Field name="ITable" type="com.sunopsis.sql.DbInt"><![CDATA[1474]]></Field>
	<Field name="ITxtColDesc" type="com.sunopsis.sql.DbInt"><![CDATA[null]]></Field>
	<Field name="LastDate" type="java.sql.Timestamp"><![CDATA[2018-05-21 01:08:04.0]]></Field>
	<Field name="LastUser" type="java.lang.String"><![CDATA[SUPERVISOR]]></Field>
	<Field name="Longc" type="com.sunopsis.sql.DbInt"><![CDATA[255]]></Field>
	<Field name="Pos" type="com.sunopsis.sql.DbInt"><![CDATA[14]]></Field>
	<Field name="RecCodeList" type="java.lang.String">null</Field>
	<Field name="Scalec" type="com.sunopsis.sql.DbInt"><![CDATA[null]]></Field>
	<Field name="ScdColType" type="java.lang.String">null</Field>
	<Field name="SourceDt" type="java.lang.String"><![CDATA[VARCHAR2]]></Field>
</Object>
<Object class="com.sunopsis.dwg.dbobj.SnpCol">
		<Field name="Bytes" type="com.sunopsis.sql.DbInt"><![CDATA[0]]></Field>
	<Field name="CheckFlow" type="java.lang.String"><![CDATA[1]]></Field>
	<Field name="CheckStat" type="java.lang.String"><![CDATA[0]]></Field>
	<Field name="ColDecSep" type="java.lang.String">null</Field>
	<Field name="ColFormat" type="java.lang.String">null</Field>
	<Field name="ColHeading" type="java.lang.String"><![CDATA[PHYSICIAN_NAME]]></Field>
	<Field name="ColMandatory" type="java.lang.String"><![CDATA[0]]></Field>
	<Field name="ColName" type="java.lang.String"><![CDATA[PHYSICIAN_NAME]]></Field>
	<Field name="ColNullIfErr" type="java.lang.String">null</Field>
	<Field name="DataFormat" type="java.lang.String">null</Field>
	<Field name="DefValue" type="java.lang.String">null</Field>
	<Field name="ExtVersion" type="java.lang.String">null</Field>
	<Field name="FilePos" type="com.sunopsis.sql.DbInt"><![CDATA[null]]></Field>
	<Field name="FirstDate" type="java.sql.Timestamp"><![CDATA[2018-05-20 00:30:51.0]]></Field>
	<Field name="FirstUser" type="java.lang.String"><![CDATA[SUPERVISOR]]></Field>
	<Field name="GlobalId" type="java.lang.String"><![CDATA[e1e1a39d-7ac8-4ed3-aeda-da5db1e31517]]></Field>
	<Field name="HbaseEncoding" type="java.lang.String">null</Field>
	<Field name="HiveSortbyPos" type="com.sunopsis.sql.DbInt"><![CDATA[null]]></Field>
	<Field name="IndChange" type="java.lang.String"><![CDATA[U]]></Field>
	<Field name="IndHiveCluster" type="java.lang.String">null</Field>
	<Field name="IndHivePartition" type="java.lang.String">null</Field>
	<Field name="IndHiveSort" type="java.lang.String">null</Field>
	<Field name="IndHiveSortbyAsc" type="java.lang.String">null</Field>
	<Field name="IndIn" type="java.lang.String">null</Field>
	<Field name="IndOut" type="java.lang.String">null</Field>
	<Field name="IndWrite" type="java.lang.String"><![CDATA[1]]></Field>
	<Field name="IndWsInsert" type="java.lang.String"><![CDATA[1]]></Field>
	<Field name="IndWsSelect" type="java.lang.String"><![CDATA[1]]></Field>
	<Field name="IndWsUpdate" type="java.lang.String"><![CDATA[1]]></Field>
	<Field name="IntVersion" type="com.sunopsis.sql.DbInt"><![CDATA[4]]></Field>
	<Field name="ICol" type="com.sunopsis.sql.DbInt"><![CDATA[13478]]></Field>
	<Field name="ISrcCol" type="com.sunopsis.sql.DbInt"><![CDATA[null]]></Field>
	<Field name="ITable" type="com.sunopsis.sql.DbInt"><![CDATA[1474]]></Field>
	<Field name="ITxtColDesc" type="com.sunopsis.sql.DbInt"><![CDATA[null]]></Field>
	<Field name="LastDate" type="java.sql.Timestamp"><![CDATA[2018-05-21 01:08:04.0]]></Field>
	<Field name="LastUser" type="java.lang.String"><![CDATA[SUPERVISOR]]></Field>
	<Field name="Longc" type="com.sunopsis.sql.DbInt"><![CDATA[10]]></Field>
	<Field name="Pos" type="com.sunopsis.sql.DbInt"><![CDATA[15]]></Field>
	<Field name="RecCodeList" type="java.lang.String">null</Field>
	<Field name="Scalec" type="com.sunopsis.sql.DbInt"><![CDATA[0]]></Field>
	<Field name="ScdColType" type="java.lang.String">null</Field>
	<Field name="SourceDt" type="java.lang.String"><![CDATA[NUMBER]]></Field>
</Object>
<Object class="com.sunopsis.dwg.dbobj.SnpCol">
		<Field name="Bytes" type="com.sunopsis.sql.DbInt"><![CDATA[0]]></Field>
	<Field name="CheckFlow" type="java.lang.String"><![CDATA[1]]></Field>
	<Field name="CheckStat" type="java.lang.String"><![CDATA[0]]></Field>
	<Field name="ColDecSep" type="java.lang.String">null</Field>
	<Field name="ColFormat" type="java.lang.String">null</Field>
	<Field name="ColHeading" type="java.lang.String"><![CDATA[PHYSICIAN_NAME_OTHER]]></Field>
	<Field name="ColMandatory" type="java.lang.String"><![CDATA[0]]></Field>
	<Field name="ColName" type="java.lang.String"><![CDATA[PHYSICIAN_NAME_OTHER]]></Field>
	<Field name="ColNullIfErr" type="java.lang.String">null</Field>
	<Field name="DataFormat" type="java.lang.String">null</Field>
	<Field name="DefValue" type="java.lang.String">null</Field>
	<Field name="ExtVersion" type="java.lang.String">null</Field>
	<Field name="FilePos" type="com.sunopsis.sql.DbInt"><![CDATA[null]]></Field>
	<Field name="FirstDate" type="java.sql.Timestamp"><![CDATA[2018-05-20 00:30:51.0]]></Field>
	<Field name="FirstUser" type="java.lang.String"><![CDATA[SUPERVISOR]]></Field>
	<Field name="GlobalId" type="java.lang.String"><![CDATA[e8aa6f2d-8fae-435e-a037-1c4c9c0b2581]]></Field>
	<Field name="HbaseEncoding" type="java.lang.String">null</Field>
	<Field name="HiveSortbyPos" type="com.sunopsis.sql.DbInt"><![CDATA[null]]></Field>
	<Field name="IndChange" type="java.lang.String"><![CDATA[U]]></Field>
	<Field name="IndHiveCluster" type="java.lang.String">null</Field>
	<Field name="IndHivePartition" type="java.lang.String">null</Field>
	<Field name="IndHiveSort" type="java.lang.String">null</Field>
	<Field name="IndHiveSortbyAsc" type="java.lang.String">null</Field>
	<Field name="IndIn" type="java.lang.String">null</Field>
	<Field name="IndOut" type="java.lang.String">null</Field>
	<Field name="IndWrite" type="java.lang.String"><![CDATA[1]]></Field>
	<Field name="IndWsInsert" type="java.lang.String"><![CDATA[1]]></Field>
	<Field name="IndWsSelect" type="java.lang.String"><![CDATA[1]]></Field>
	<Field name="IndWsUpdate" type="java.lang.String"><![CDATA[1]]></Field>
	<Field name="IntVersion" type="com.sunopsis.sql.DbInt"><![CDATA[4]]></Field>
	<Field name="ICol" type="com.sunopsis.sql.DbInt"><![CDATA[13479]]></Field>
	<Field name="ISrcCol" type="com.sunopsis.sql.DbInt"><![CDATA[null]]></Field>
	<Field name="ITable" type="com.sunopsis.sql.DbInt"><![CDATA[1474]]></Field>
	<Field name="ITxtColDesc" type="com.sunopsis.sql.DbInt"><![CDATA[null]]></Field>
	<Field name="LastDate" type="java.sql.Timestamp"><![CDATA[2018-05-21 01:08:04.0]]></Field>
	<Field name="LastUser" type="java.lang.String"><![CDATA[SUPERVISOR]]></Field>
	<Field name="Longc" type="com.sunopsis.sql.DbInt"><![CDATA[255]]></Field>
	<Field name="Pos" type="com.sunopsis.sql.DbInt"><![CDATA[16]]></Field>
	<Field name="RecCodeList" type="java.lang.String">null</Field>
	<Field name="Scalec" type="com.sunopsis.sql.DbInt"><![CDATA[null]]></Field>
	<Field name="ScdColType" type="java.lang.String">null</Field>
	<Field name="SourceDt" type="java.lang.String"><![CDATA[VARCHAR2]]></Field>
</Object>
<Object class="com.sunopsis.dwg.dbobj.SnpCol">
		<Field name="Bytes" type="com.sunopsis.sql.DbInt"><![CDATA[0]]></Field>
	<Field name="CheckFlow" type="java.lang.String"><![CDATA[1]]></Field>
	<Field name="CheckStat" type="java.lang.String"><![CDATA[0]]></Field>
	<Field name="ColDecSep" type="java.lang.String">null</Field>
	<Field name="ColFormat" type="java.lang.String">null</Field>
	<Field name="ColHeading" type="java.lang.String"><![CDATA[PHYSICIAN_NAME_OTHER_TITLE]]></Field>
	<Field name="ColMandatory" type="java.lang.String"><![CDATA[0]]></Field>
	<Field name="ColName" type="java.lang.String"><![CDATA[PHYSICIAN_NAME_OTHER_TITLE]]></Field>
	<Field name="ColNullIfErr" type="java.lang.String">null</Field>
	<Field name="DataFormat" type="java.lang.String">null</Field>
	<Field name="DefValue" type="java.lang.String">null</Field>
	<Field name="ExtVersion" type="java.lang.String">null</Field>
	<Field name="FilePos" type="com.sunopsis.sql.DbInt"><![CDATA[null]]></Field>
	<Field name="FirstDate" type="java.sql.Timestamp"><![CDATA[2018-05-20 00:30:51.0]]></Field>
	<Field name="FirstUser" type="java.lang.String"><![CDATA[SUPERVISOR]]></Field>
	<Field name="GlobalId" type="java.lang.String"><![CDATA[126df71b-657f-45b8-8791-31d16bf4d5b5]]></Field>
	<Field name="HbaseEncoding" type="java.lang.String">null</Field>
	<Field name="HiveSortbyPos" type="com.sunopsis.sql.DbInt"><![CDATA[null]]></Field>
	<Field name="IndChange" type="java.lang.String"><![CDATA[U]]></Field>
	<Field name="IndHiveCluster" type="java.lang.String">null</Field>
	<Field name="IndHivePartition" type="java.lang.String">null</Field>
	<Field name="IndHiveSort" type="java.lang.String">null</Field>
	<Field name="IndHiveSortbyAsc" type="java.lang.String">null</Field>
	<Field name="IndIn" type="java.lang.String">null</Field>
	<Field name="IndOut" type="java.lang.String">null</Field>
	<Field name="IndWrite" type="java.lang.String"><![CDATA[1]]></Field>
	<Field name="IndWsInsert" type="java.lang.String"><![CDATA[1]]></Field>
	<Field name="IndWsSelect" type="java.lang.String"><![CDATA[1]]></Field>
	<Field name="IndWsUpdate" type="java.lang.String"><![CDATA[1]]></Field>
	<Field name="IntVersion" type="com.sunopsis.sql.DbInt"><![CDATA[4]]></Field>
	<Field name="ICol" type="com.sunopsis.sql.DbInt"><![CDATA[13480]]></Field>
	<Field name="ISrcCol" type="com.sunopsis.sql.DbInt"><![CDATA[null]]></Field>
	<Field name="ITable" type="com.sunopsis.sql.DbInt"><![CDATA[1474]]></Field>
	<Field name="ITxtColDesc" type="com.sunopsis.sql.DbInt"><![CDATA[null]]></Field>
	<Field name="LastDate" type="java.sql.Timestamp"><![CDATA[2018-05-21 01:08:04.0]]></Field>
	<Field name="LastUser" type="java.lang.String"><![CDATA[SUPERVISOR]]></Field>
	<Field name="Longc" type="com.sunopsis.sql.DbInt"><![CDATA[255]]></Field>
	<Field name="Pos" type="com.sunopsis.sql.DbInt"><![CDATA[17]]></Field>
	<Field name="RecCodeList" type="java.lang.String">null</Field>
	<Field name="Scalec" type="com.sunopsis.sql.DbInt"><![CDATA[null]]></Field>
	<Field name="ScdColType" type="java.lang.String">null</Field>
	<Field name="SourceDt" type="java.lang.String"><![CDATA[VARCHAR2]]></Field>
</Object>
<Object class="com.sunopsis.dwg.dbobj.SnpCol">
		<Field name="Bytes" type="com.sunopsis.sql.DbInt"><![CDATA[0]]></Field>
	<Field name="CheckFlow" type="java.lang.String"><![CDATA[1]]></Field>
	<Field name="CheckStat" type="java.lang.String"><![CDATA[0]]></Field>
	<Field name="ColDecSep" type="java.lang.String">null</Field>
	<Field name="ColFormat" type="java.lang.String">null</Field>
	<Field name="ColHeading" type="java.lang.String"><![CDATA[PRN_OR_EMERGENCY]]></Field>
	<Field name="ColMandatory" type="java.lang.String"><![CDATA[0]]></Field>
	<Field name="ColName" type="java.lang.String"><![CDATA[PRN_OR_EMERGENCY]]></Field>
	<Field name="ColNullIfErr" type="java.lang.String">null</Field>
	<Field name="DataFormat" type="java.lang.String">null</Field>
	<Field name="DefValue" type="java.lang.String">null</Field>
	<Field name="ExtVersion" type="java.lang.String">null</Field>
	<Field name="FilePos" type="com.sunopsis.sql.DbInt"><![CDATA[null]]></Field>
	<Field name="FirstDate" type="java.sql.Timestamp"><![CDATA[2018-05-20 00:30:51.0]]></Field>
	<Field name="FirstUser" type="java.lang.String"><![CDATA[SUPERVISOR]]></Field>
	<Field name="GlobalId" type="java.lang.String"><![CDATA[77348c40-648f-493d-b6a3-6fd7f467ceb0]]></Field>
	<Field name="HbaseEncoding" type="java.lang.String">null</Field>
	<Field name="HiveSortbyPos" type="com.sunopsis.sql.DbInt"><![CDATA[null]]></Field>
	<Field name="IndChange" type="java.lang.String"><![CDATA[U]]></Field>
	<Field name="IndHiveCluster" type="java.lang.String">null</Field>
	<Field name="IndHivePartition" type="java.lang.String">null</Field>
	<Field name="IndHiveSort" type="java.lang.String">null</Field>
	<Field name="IndHiveSortbyAsc" type="java.lang.String">null</Field>
	<Field name="IndIn" type="java.lang.String">null</Field>
	<Field name="IndOut" type="java.lang.String">null</Field>
	<Field name="IndWrite" type="java.lang.String"><![CDATA[1]]></Field>
	<Field name="IndWsInsert" type="java.lang.String"><![CDATA[1]]></Field>
	<Field name="IndWsSelect" type="java.lang.String"><![CDATA[1]]></Field>
	<Field name="IndWsUpdate" type="java.lang.String"><![CDATA[1]]></Field>
	<Field name="IntVersion" type="com.sunopsis.sql.DbInt"><![CDATA[4]]></Field>
	<Field name="ICol" type="com.sunopsis.sql.DbInt"><![CDATA[13481]]></Field>
	<Field name="ISrcCol" type="com.sunopsis.sql.DbInt"><![CDATA[null]]></Field>
	<Field name="ITable" type="com.sunopsis.sql.DbInt"><![CDATA[1474]]></Field>
	<Field name="ITxtColDesc" type="com.sunopsis.sql.DbInt"><![CDATA[null]]></Field>
	<Field name="LastDate" type="java.sql.Timestamp"><![CDATA[2018-05-21 01:08:04.0]]></Field>
	<Field name="LastUser" type="java.lang.String"><![CDATA[SUPERVISOR]]></Field>
	<Field name="Longc" type="com.sunopsis.sql.DbInt"><![CDATA[1]]></Field>
	<Field name="Pos" type="com.sunopsis.sql.DbInt"><![CDATA[18]]></Field>
	<Field name="RecCodeList" type="java.lang.String">null</Field>
	<Field name="Scalec" type="com.sunopsis.sql.DbInt"><![CDATA[0]]></Field>
	<Field name="ScdColType" type="java.lang.String">null</Field>
	<Field name="SourceDt" type="java.lang.String"><![CDATA[NUMBER]]></Field>
</Object>
<Object class="com.sunopsis.dwg.dbobj.SnpCol">
		<Field name="Bytes" type="com.sunopsis.sql.DbInt"><![CDATA[0]]></Field>
	<Field name="CheckFlow" type="java.lang.String"><![CDATA[1]]></Field>
	<Field name="CheckStat" type="java.lang.String"><![CDATA[0]]></Field>
	<Field name="ColDecSep" type="java.lang.String">null</Field>
	<Field name="ColFormat" type="java.lang.String">null</Field>
	<Field name="ColHeading" type="java.lang.String"><![CDATA[LOCATION]]></Field>
	<Field name="ColMandatory" type="java.lang.String"><![CDATA[0]]></Field>
	<Field name="ColName" type="java.lang.String"><![CDATA[LOCATION]]></Field>
	<Field name="ColNullIfErr" type="java.lang.String">null</Field>
	<Field name="DataFormat" type="java.lang.String">null</Field>
	<Field name="DefValue" type="java.lang.String">null</Field>
	<Field name="ExtVersion" type="java.lang.String">null</Field>
	<Field name="FilePos" type="com.sunopsis.sql.DbInt"><![CDATA[null]]></Field>
	<Field name="FirstDate" type="java.sql.Timestamp"><![CDATA[2018-05-20 00:30:51.0]]></Field>
	<Field name="FirstUser" type="java.lang.String"><![CDATA[SUPERVISOR]]></Field>
	<Field name="GlobalId" type="java.lang.String"><![CDATA[a9c12fc7-b2e0-4579-93ac-d25814d7fb77]]></Field>
	<Field name="HbaseEncoding" type="java.lang.String">null</Field>
	<Field name="HiveSortbyPos" type="com.sunopsis.sql.DbInt"><![CDATA[null]]></Field>
	<Field name="IndChange" type="java.lang.String"><![CDATA[U]]></Field>
	<Field name="IndHiveCluster" type="java.lang.String">null</Field>
	<Field name="IndHivePartition" type="java.lang.String">null</Field>
	<Field name="IndHiveSort" type="java.lang.String">null</Field>
	<Field name="IndHiveSortbyAsc" type="java.lang.String">null</Field>
	<Field name="IndIn" type="java.lang.String">null</Field>
	<Field name="IndOut" type="java.lang.String">null</Field>
	<Field name="IndWrite" type="java.lang.String"><![CDATA[1]]></Field>
	<Field name="IndWsInsert" type="java.lang.String"><![CDATA[1]]></Field>
	<Field name="IndWsSelect" type="java.lang.String"><![CDATA[1]]></Field>
	<Field name="IndWsUpdate" type="java.lang.String"><![CDATA[1]]></Field>
	<Field name="IntVersion" type="com.sunopsis.sql.DbInt"><![CDATA[4]]></Field>
	<Field name="ICol" type="com.sunopsis.sql.DbInt"><![CDATA[13482]]></Field>
	<Field name="ISrcCol" type="com.sunopsis.sql.DbInt"><![CDATA[null]]></Field>
	<Field name="ITable" type="com.sunopsis.sql.DbInt"><![CDATA[1474]]></Field>
	<Field name="ITxtColDesc" type="com.sunopsis.sql.DbInt"><![CDATA[null]]></Field>
	<Field name="LastDate" type="java.sql.Timestamp"><![CDATA[2018-05-21 01:08:04.0]]></Field>
	<Field name="LastUser" type="java.lang.String"><![CDATA[SUPERVISOR]]></Field>
	<Field name="Longc" type="com.sunopsis.sql.DbInt"><![CDATA[10]]></Field>
	<Field name="Pos" type="com.sunopsis.sql.DbInt"><![CDATA[19]]></Field>
	<Field name="RecCodeList" type="java.lang.String">null</Field>
	<Field name="Scalec" type="com.sunopsis.sql.DbInt"><![CDATA[0]]></Field>
	<Field name="ScdColType" type="java.lang.String">null</Field>
	<Field name="SourceDt" type="java.lang.String"><![CDATA[NUMBER]]></Field>
</Object>
<Object class="com.sunopsis.dwg.dbobj.SnpCol">
		<Field name="Bytes" type="com.sunopsis.sql.DbInt"><![CDATA[0]]></Field>
	<Field name="CheckFlow" type="java.lang.String"><![CDATA[1]]></Field>
	<Field name="CheckStat" type="java.lang.String"><![CDATA[0]]></Field>
	<Field name="ColDecSep" type="java.lang.String">null</Field>
	<Field name="ColFormat" type="java.lang.String">null</Field>
	<Field name="ColHeading" type="java.lang.String"><![CDATA[BEGIN_TIME]]></Field>
	<Field name="ColMandatory" type="java.lang.String"><![CDATA[0]]></Field>
	<Field name="ColName" type="java.lang.String"><![CDATA[BEGIN_TIME]]></Field>
	<Field name="ColNullIfErr" type="java.lang.String">null</Field>
	<Field name="DataFormat" type="java.lang.String">null</Field>
	<Field name="DefValue" type="java.lang.String">null</Field>
	<Field name="ExtVersion" type="java.lang.String">null</Field>
	<Field name="FilePos" type="com.sunopsis.sql.DbInt"><![CDATA[null]]></Field>
	<Field name="FirstDate" type="java.sql.Timestamp"><![CDATA[2018-05-20 00:30:51.0]]></Field>
	<Field name="FirstUser" type="java.lang.String"><![CDATA[SUPERVISOR]]></Field>
	<Field name="GlobalId" type="java.lang.String"><![CDATA[05569b81-8c51-4790-aaa2-625526ab8eea]]></Field>
	<Field name="HbaseEncoding" type="java.lang.String">null</Field>
	<Field name="HiveSortbyPos" type="com.sunopsis.sql.DbInt"><![CDATA[null]]></Field>
	<Field name="IndChange" type="java.lang.String"><![CDATA[U]]></Field>
	<Field name="IndHiveCluster" type="java.lang.String">null</Field>
	<Field name="IndHivePartition" type="java.lang.String">null</Field>
	<Field name="IndHiveSort" type="java.lang.String">null</Field>
	<Field name="IndHiveSortbyAsc" type="java.lang.String">null</Field>
	<Field name="IndIn" type="java.lang.String">null</Field>
	<Field name="IndOut" type="java.lang.String">null</Field>
	<Field name="IndWrite" type="java.lang.String"><![CDATA[1]]></Field>
	<Field name="IndWsInsert" type="java.lang.String"><![CDATA[1]]></Field>
	<Field name="IndWsSelect" type="java.lang.String"><![CDATA[1]]></Field>
	<Field name="IndWsUpdate" type="java.lang.String"><![CDATA[1]]></Field>
	<Field name="IntVersion" type="com.sunopsis.sql.DbInt"><![CDATA[4]]></Field>
	<Field name="ICol" type="com.sunopsis.sql.DbInt"><![CDATA[13483]]></Field>
	<Field name="ISrcCol" type="com.sunopsis.sql.DbInt"><![CDATA[null]]></Field>
	<Field name="ITable" type="com.sunopsis.sql.DbInt"><![CDATA[1474]]></Field>
	<Field name="ITxtColDesc" type="com.sunopsis.sql.DbInt"><![CDATA[null]]></Field>
	<Field name="LastDate" type="java.sql.Timestamp"><![CDATA[2018-05-21 01:08:04.0]]></Field>
	<Field name="LastUser" type="java.lang.String"><![CDATA[SUPERVISOR]]></Field>
	<Field name="Longc" type="com.sunopsis.sql.DbInt"><![CDATA[8]]></Field>
	<Field name="Pos" type="com.sunopsis.sql.DbInt"><![CDATA[20]]></Field>
	<Field name="RecCodeList" type="java.lang.String">null</Field>
	<Field name="Scalec" type="com.sunopsis.sql.DbInt"><![CDATA[null]]></Field>
	<Field name="ScdColType" type="java.lang.String">null</Field>
	<Field name="SourceDt" type="java.lang.String"><![CDATA[VARCHAR2]]></Field>
</Object>
<Object class="com.sunopsis.dwg.dbobj.SnpCol">
		<Field name="Bytes" type="com.sunopsis.sql.DbInt"><![CDATA[0]]></Field>
	<Field name="CheckFlow" type="java.lang.String"><![CDATA[1]]></Field>
	<Field name="CheckStat" type="java.lang.String"><![CDATA[0]]></Field>
	<Field name="ColDecSep" type="java.lang.String">null</Field>
	<Field name="ColFormat" type="java.lang.String">null</Field>
	<Field name="ColHeading" type="java.lang.String"><![CDATA[END_TIME]]></Field>
	<Field name="ColMandatory" type="java.lang.String"><![CDATA[0]]></Field>
	<Field name="ColName" type="java.lang.String"><![CDATA[END_TIME]]></Field>
	<Field name="ColNullIfErr" type="java.lang.String">null</Field>
	<Field name="DataFormat" type="java.lang.String">null</Field>
	<Field name="DefValue" type="java.lang.String">null</Field>
	<Field name="ExtVersion" type="java.lang.String">null</Field>
	<Field name="FilePos" type="com.sunopsis.sql.DbInt"><![CDATA[null]]></Field>
	<Field name="FirstDate" type="java.sql.Timestamp"><![CDATA[2018-05-20 00:30:51.0]]></Field>
	<Field name="FirstUser" type="java.lang.String"><![CDATA[SUPERVISOR]]></Field>
	<Field name="GlobalId" type="java.lang.String"><![CDATA[ca06ecab-413b-4177-8e67-7d185a57eb5d]]></Field>
	<Field name="HbaseEncoding" type="java.lang.String">null</Field>
	<Field name="HiveSortbyPos" type="com.sunopsis.sql.DbInt"><![CDATA[null]]></Field>
	<Field name="IndChange" type="java.lang.String"><![CDATA[U]]></Field>
	<Field name="IndHiveCluster" type="java.lang.String">null</Field>
	<Field name="IndHivePartition" type="java.lang.String">null</Field>
	<Field name="IndHiveSort" type="java.lang.String">null</Field>
	<Field name="IndHiveSortbyAsc" type="java.lang.String">null</Field>
	<Field name="IndIn" type="java.lang.String">null</Field>
	<Field name="IndOut" type="java.lang.String">null</Field>
	<Field name="IndWrite" type="java.lang.String"><![CDATA[1]]></Field>
	<Field name="IndWsInsert" type="java.lang.String"><![CDATA[1]]></Field>
	<Field name="IndWsSelect" type="java.lang.String"><![CDATA[1]]></Field>
	<Field name="IndWsUpdate" type="java.lang.String"><![CDATA[1]]></Field>
	<Field name="IntVersion" type="com.sunopsis.sql.DbInt"><![CDATA[4]]></Field>
	<Field name="ICol" type="com.sunopsis.sql.DbInt"><![CDATA[13484]]></Field>
	<Field name="ISrcCol" type="com.sunopsis.sql.DbInt"><![CDATA[null]]></Field>
	<Field name="ITable" type="com.sunopsis.sql.DbInt"><![CDATA[1474]]></Field>
	<Field name="ITxtColDesc" type="com.sunopsis.sql.DbInt"><![CDATA[null]]></Field>
	<Field name="LastDate" type="java.sql.Timestamp"><![CDATA[2018-05-21 01:08:04.0]]></Field>
	<Field name="LastUser" type="java.lang.String"><![CDATA[SUPERVISOR]]></Field>
	<Field name="Longc" type="com.sunopsis.sql.DbInt"><![CDATA[8]]></Field>
	<Field name="Pos" type="com.sunopsis.sql.DbInt"><![CDATA[21]]></Field>
	<Field name="RecCodeList" type="java.lang.String">null</Field>
	<Field name="Scalec" type="com.sunopsis.sql.DbInt"><![CDATA[null]]></Field>
	<Field name="ScdColType" type="java.lang.String">null</Field>
	<Field name="SourceDt" type="java.lang.String"><![CDATA[VARCHAR2]]></Field>
</Object>
<Object class="com.sunopsis.dwg.dbobj.SnpKey">
		<Field name="CheckFlow" type="java.lang.String"><![CDATA[1]]></Field>
	<Field name="CheckStat" type="java.lang.String"><![CDATA[1]]></Field>
	<Field name="ConsType" type="java.lang.String"><![CDATA[PK]]></Field>
	<Field name="ExtVersion" type="java.lang.String">null</Field>
	<Field name="FirstDate" type="java.sql.Timestamp"><![CDATA[2018-05-20 00:30:51.0]]></Field>
	<Field name="FirstUser" type="java.lang.String"><![CDATA[SUPERVISOR]]></Field>
	<Field name="GlobalId" type="java.lang.String"><![CDATA[37e2b160-7c0d-4cca-a0b1-aacda3c018ce]]></Field>
	<Field name="IndActive" type="java.lang.String"><![CDATA[1]]></Field>
	<Field name="IndChange" type="java.lang.String"><![CDATA[U]]></Field>
	<Field name="IndDb" type="java.lang.String"><![CDATA[1]]></Field>
	<Field name="IntVersion" type="com.sunopsis.sql.DbInt"><![CDATA[4]]></Field>
	<Field name="IKey" type="com.sunopsis.sql.DbInt"><![CDATA[506]]></Field>
	<Field name="ITable" type="com.sunopsis.sql.DbInt"><![CDATA[1474]]></Field>
	<Field name="KeyName" type="java.lang.String"><![CDATA[SYS_C0014406]]></Field>
	<Field name="LastDate" type="java.sql.Timestamp"><![CDATA[2018-05-21 01:08:04.0]]></Field>
	<Field name="LastUser" type="java.lang.String"><![CDATA[SUPERVISOR]]></Field>
</Object>
<Object class="com.sunopsis.dwg.dbobj.SnpKeyCol">
		<Field name="FirstDate" type="java.sql.Timestamp"><![CDATA[2018-05-20 00:30:51.0]]></Field>
	<Field name="FirstUser" type="java.lang.String"><![CDATA[SUPERVISOR]]></Field>
	<Field name="GlobalId" type="java.lang.String"><![CDATA[30f574f7-d931-486f-bfeb-5bf085a53591]]></Field>
	<Field name="IndChange" type="java.lang.String"><![CDATA[U]]></Field>
	<Field name="IntVersion" type="com.sunopsis.sql.DbInt"><![CDATA[4]]></Field>
	<Field name="ICol" type="com.sunopsis.sql.DbInt"><![CDATA[13464]]></Field>
	<Field name="IKey" type="com.sunopsis.sql.DbInt"><![CDATA[506]]></Field>
	<Field name="LastDate" type="java.sql.Timestamp"><![CDATA[2018-05-21 01:08:04.0]]></Field>
	<Field name="LastUser" type="java.lang.String"><![CDATA[SUPERVISOR]]></Field>
	<Field name="Pos" type="com.sunopsis.sql.DbInt"><![CDATA[1]]></Field>
</Object>
<Object class="com.sunopsis.dwg.dbobj.SnpReferencedObject">
		<Field name="IObject" type="com.sunopsis.sql.DbInt"><![CDATA[2600]]></Field>
	<Field name="ObjectPKasString" type="java.lang.String"><![CDATA[13464]]></Field>
	<Field name="ObjectAKasString" type="java.lang.String"><![CDATA[1474#ID]]></Field>
	<Field name="Description" type="java.lang.String"><![CDATA[SNP_MODFOLDER : WAREHOUSE_DATASOURCE #SNP_MODEL : PROD7 #SNP_SUBMODEL : GER #SNP_TABLE : GER_EVENT_RESTRAINT_OTHER #SNP_COL : ID]]></Field>
 <Field name="GlobalId" type="java.lang.String"><![CDATA[b6441642-0ab0-4e6c-a2ef-de91e07cfbbf]]></Field>
</Object>
<Object class="com.sunopsis.dwg.dbobj.SnpJoin">
		<Field name="CheckFlow" type="java.lang.String"><![CDATA[1]]></Field>
	<Field name="CheckStat" type="java.lang.String"><![CDATA[1]]></Field>
	<Field name="Defer" type="java.lang.String">null</Field>
	<Field name="DelRule" type="java.lang.String"><![CDATA[R]]></Field>
	<Field name="ExtVersion" type="java.lang.String">null</Field>
	<Field name="FirstDate" type="java.sql.Timestamp"><![CDATA[2018-05-20 00:30:51.0]]></Field>
	<Field name="FirstUser" type="java.lang.String"><![CDATA[SUPERVISOR]]></Field>
	<Field name="FkName" type="java.lang.String"><![CDATA[FKDE86E6CD83ACFC51]]></Field>
	<Field name="FkType" type="java.lang.String"><![CDATA[D]]></Field>
	<Field name="GlobalId" type="java.lang.String"><![CDATA[be15d499-f4cb-4539-b6b5-626f80ef296e]]></Field>
	<Field name="IndActive" type="java.lang.String"><![CDATA[1]]></Field>
	<Field name="IndChange" type="java.lang.String"><![CDATA[U]]></Field>
	<Field name="IntVersion" type="com.sunopsis.sql.DbInt"><![CDATA[5]]></Field>
	<Field name="IJoin" type="com.sunopsis.sql.DbInt"><![CDATA[663]]></Field>
	<Field name="IScTablePk" type="com.sunopsis.sql.DbInt"><![CDATA[null]]></Field>
	<Field name="ITableFk" type="com.sunopsis.sql.DbInt"><![CDATA[1474]]></Field>
	<Field name="ITablePk" type="com.sunopsis.sql.DbInt"><![CDATA[1480]]></Field>
	<Field name="ITxtComplex" type="com.sunopsis.sql.DbInt"><![CDATA[null]]></Field>
	<Field name="LastDate" type="java.sql.Timestamp"><![CDATA[2018-05-21 01:08:04.0]]></Field>
	<Field name="LastUser" type="java.lang.String"><![CDATA[SUPERVISOR]]></Field>
	<Field name="PkCatalog" type="java.lang.String">null</Field>
	<Field name="PkIMod" type="com.sunopsis.sql.DbInt"><![CDATA[38]]></Field>
	<Field name="PkSchema" type="java.lang.String"><![CDATA[PROD7]]></Field>
	<Field name="PkTableAlias" type="java.lang.String"><![CDATA[GER_GENERAL_EVENT]]></Field>
	<Field name="PkTableName" type="java.lang.String"><![CDATA[GER_GENERAL_EVENT]]></Field>
	<Field name="UpdRule" type="java.lang.String"><![CDATA[C]]></Field>
</Object>
<Object class="com.sunopsis.dwg.dbobj.SnpReferencedObject">
		<Field name="IObject" type="com.sunopsis.sql.DbInt"><![CDATA[2400]]></Field>
	<Field name="ObjectPKasString" type="java.lang.String"><![CDATA[1480]]></Field>
	<Field name="ObjectAKasString" type="java.lang.String"><![CDATA[38#GER_GENERAL_EVENT]]></Field>
	<Field name="Description" type="java.lang.String"><![CDATA[SNP_MODFOLDER : WAREHOUSE_DATASOURCE #SNP_MODEL : PROD7 #SNP_SUBMODEL : GER #SNP_TABLE : GER_GENERAL_EVENT]]></Field>
 <Field name="GlobalId" type="java.lang.String"><![CDATA[575c2a0b-fdb7-4348-908e-eab1d0862ef1]]></Field>
</Object>
<Object class="com.sunopsis.dwg.dbobj.SnpJoinCol">
		<Field name="FirstDate" type="java.sql.Timestamp"><![CDATA[2018-05-21 01:08:04.0]]></Field>
	<Field name="FirstUser" type="java.lang.String"><![CDATA[SUPERVISOR]]></Field>
	<Field name="GlobalId" type="java.lang.String"><![CDATA[d36c958f-a17c-41b2-933a-86d05208cdcc]]></Field>
	<Field name="IndChange" type="java.lang.String"><![CDATA[I]]></Field>
	<Field name="IntVersion" type="com.sunopsis.sql.DbInt"><![CDATA[1]]></Field>
	<Field name="IColFk" type="com.sunopsis.sql.DbInt"><![CDATA[13464]]></Field>
	<Field name="IColPk" type="com.sunopsis.sql.DbInt"><![CDATA[13548]]></Field>
	<Field name="IJoin" type="com.sunopsis.sql.DbInt"><![CDATA[663]]></Field>
	<Field name="LastDate" type="java.sql.Timestamp"><![CDATA[2018-05-21 01:08:04.0]]></Field>
	<Field name="LastUser" type="java.lang.String"><![CDATA[SUPERVISOR]]></Field>
	<Field name="PkColName" type="java.lang.String"><![CDATA[ID]]></Field>
	<Field name="Pos" type="com.sunopsis.sql.DbInt"><![CDATA[1]]></Field>
</Object>
<Object class="com.sunopsis.dwg.dbobj.SnpReferencedObject">
		<Field name="IObject" type="com.sunopsis.sql.DbInt"><![CDATA[2600]]></Field>
	<Field name="ObjectPKasString" type="java.lang.String"><![CDATA[13548]]></Field>
	<Field name="ObjectAKasString" type="java.lang.String"><![CDATA[1480#ID]]></Field>
	<Field name="Description" type="java.lang.String"><![CDATA[SNP_MODFOLDER : WAREHOUSE_DATASOURCE #SNP_MODEL : PROD7 #SNP_SUBMODEL : GER #SNP_TABLE : GER_GENERAL_EVENT #SNP_COL : ID]]></Field>
 <Field name="GlobalId" type="java.lang.String"><![CDATA[b7afb275-fdb6-4dd8-a4cb-e1ea2bb332a5]]></Field>
</Object>
<Object class="com.sunopsis.dwg.dbobj.SnpReferencedObject">
		<Field name="IObject" type="com.sunopsis.sql.DbInt"><![CDATA[2600]]></Field>
	<Field name="ObjectPKasString" type="java.lang.String"><![CDATA[13464]]></Field>
	<Field name="ObjectAKasString" type="java.lang.String"><![CDATA[1474#ID]]></Field>
	<Field name="Description" type="java.lang.String"><![CDATA[SNP_MODFOLDER : WAREHOUSE_DATASOURCE #SNP_MODEL : PROD7 #SNP_SUBMODEL : GER #SNP_TABLE : GER_EVENT_RESTRAINT_OTHER #SNP_COL : ID]]></Field>
 <Field name="GlobalId" type="java.lang.String"><![CDATA[b6441642-0ab0-4e6c-a2ef-de91e07cfbbf]]></Field>
</Object>
<Object class="com.sunopsis.dwg.dbobj.SnpFKXRef">
		<Field name="RefKey" type="java.lang.String"><![CDATA[SNP_SUBMODEL.38.131]]></Field>
	<Field name="RefObjGlobalId" type="java.lang.String"><![CDATA[ec05e5b0-f3b1-4a04-8259-11bc1acb8ed6]]></Field>
 <Field name="RefObjFQName" type="java.lang.String"><![CDATA[WAREHOUSE_DATASOURCE.PROD7.GER]]></Field>
 <Field name="RefObjFQType" type="java.lang.String"><![CDATA[SNP_MODFOLDER.SNP_MODEL.SNP_SUBMODEL]]></Field>
 <Field name="RefObjFQNameLengths" type="java.lang.String"><![CDATA[20.5.3]]></Field>
</Object>
<Object class="com.sunopsis.dwg.dbobj.SnpFKXRef">
		<Field name="RefKey" type="java.lang.String"><![CDATA[SNP_TABLE.1474]]></Field>
	<Field name="RefObjGlobalId" type="java.lang.String"><![CDATA[5bef048a-c388-40bc-a2a0-a7c007baf5f9]]></Field>
 <Field name="RefObjFQName" type="java.lang.String"><![CDATA[WAREHOUSE_DATASOURCE.PROD7.GER.GER_EVENT_RESTRAINT_OTHER]]></Field>
 <Field name="RefObjFQType" type="java.lang.String"><![CDATA[SNP_MODFOLDER.SNP_MODEL.SNP_SUBMODEL.SNP_TABLE]]></Field>
 <Field name="RefObjFQNameLengths" type="java.lang.String"><![CDATA[20.5.3.25]]></Field>
</Object>
<Object class="com.sunopsis.dwg.dbobj.SnpFKXRef">
		<Field name="RefKey" type="java.lang.String"><![CDATA[SNP_KEY.506]]></Field>
	<Field name="RefObjGlobalId" type="java.lang.String"><![CDATA[37e2b160-7c0d-4cca-a0b1-aacda3c018ce]]></Field>
 <Field name="RefObjFQName" type="java.lang.String"><![CDATA[WAREHOUSE_DATASOURCE.PROD7.GER.GER_EVENT_RESTRAINT_OTHER.SYS_C0014406]]></Field>
 <Field name="RefObjFQType" type="java.lang.String"><![CDATA[SNP_MODFOLDER.SNP_MODEL.SNP_SUBMODEL.SNP_TABLE.SNP_KEY]]></Field>
 <Field name="RefObjFQNameLengths" type="java.lang.String"><![CDATA[20.5.3.25.12]]></Field>
</Object>
<Object class="com.sunopsis.dwg.dbobj.SnpFKXRef">
		<Field name="RefKey" type="java.lang.String"><![CDATA[SNP_COL.13464]]></Field>
	<Field name="RefObjGlobalId" type="java.lang.String"><![CDATA[b6441642-0ab0-4e6c-a2ef-de91e07cfbbf]]></Field>
 <Field name="RefObjFQName" type="java.lang.String"><![CDATA[WAREHOUSE_DATASOURCE.PROD7.GER.GER_EVENT_RESTRAINT_OTHER.ID]]></Field>
 <Field name="RefObjFQType" type="java.lang.String"><![CDATA[SNP_MODFOLDER.SNP_MODEL.SNP_SUBMODEL.SNP_TABLE.SNP_COL]]></Field>
 <Field name="RefObjFQNameLengths" type="java.lang.String"><![CDATA[20.5.3.25.2]]></Field>
</Object>
<Object class="com.sunopsis.dwg.dbobj.SnpFKXRef">
		<Field name="RefKey" type="java.lang.String"><![CDATA[SNP_TABLE.1480]]></Field>
	<Field name="RefObjGlobalId" type="java.lang.String"><![CDATA[575c2a0b-fdb7-4348-908e-eab1d0862ef1]]></Field>
 <Field name="RefObjFQName" type="java.lang.String"><![CDATA[WAREHOUSE_DATASOURCE.PROD7.GER.GER_GENERAL_EVENT]]></Field>
 <Field name="RefObjFQType" type="java.lang.String"><![CDATA[SNP_MODFOLDER.SNP_MODEL.SNP_SUBMODEL.SNP_TABLE]]></Field>
 <Field name="RefObjFQNameLengths" type="java.lang.String"><![CDATA[20.5.3.17]]></Field>
</Object>
<Object class="com.sunopsis.dwg.dbobj.SnpFKXRef">
		<Field name="RefKey" type="java.lang.String"><![CDATA[SNP_TABLE.1480]]></Field>
	<Field name="RefObjGlobalId" type="java.lang.String"><![CDATA[575c2a0b-fdb7-4348-908e-eab1d0862ef1]]></Field>
 <Field name="RefObjFQName" type="java.lang.String"><![CDATA[WAREHOUSE_DATASOURCE.PROD7.GER.GER_GENERAL_EVENT]]></Field>
 <Field name="RefObjFQType" type="java.lang.String"><![CDATA[SNP_MODFOLDER.SNP_MODEL.SNP_SUBMODEL.SNP_TABLE]]></Field>
 <Field name="RefObjFQNameLengths" type="java.lang.String"><![CDATA[20.5.3.17]]></Field>
</Object>
<Object class="com.sunopsis.dwg.dbobj.SnpFKXRef">
		<Field name="RefKey" type="java.lang.String"><![CDATA[SNP_MODEL.38]]></Field>
	<Field name="RefObjGlobalId" type="java.lang.String"><![CDATA[efeff4dc-6d16-4080-8af0-ecabf71021da]]></Field>
 <Field name="RefObjFQName" type="java.lang.String"><![CDATA[WAREHOUSE_DATASOURCE.PROD7]]></Field>
 <Field name="RefObjFQType" type="java.lang.String"><![CDATA[SNP_MODFOLDER.SNP_MODEL]]></Field>
 <Field name="RefObjFQNameLengths" type="java.lang.String"><![CDATA[20.5]]></Field>
</Object>
<Object class="com.sunopsis.dwg.dbobj.SnpFKXRef">
		<Field name="RefKey" type="java.lang.String"><![CDATA[SNP_JOIN.663]]></Field>
	<Field name="RefObjGlobalId" type="java.lang.String"><![CDATA[be15d499-f4cb-4539-b6b5-626f80ef296e]]></Field>
 <Field name="RefObjFQName" type="java.lang.String"><![CDATA[WAREHOUSE_DATASOURCE.PROD7.GER.GER_EVENT_RESTRAINT_OTHER.FKDE86E6CD83ACFC51]]></Field>
 <Field name="RefObjFQType" type="java.lang.String"><![CDATA[SNP_MODFOLDER.SNP_MODEL.SNP_SUBMODEL.SNP_TABLE.SNP_JOIN]]></Field>
 <Field name="RefObjFQNameLengths" type="java.lang.String"><![CDATA[20.5.3.25.18]]></Field>
</Object>
<Object class="com.sunopsis.dwg.dbobj.SnpFKXRef">
		<Field name="RefKey" type="java.lang.String"><![CDATA[SNP_COL.13548]]></Field>
	<Field name="RefObjGlobalId" type="java.lang.String"><![CDATA[b7afb275-fdb6-4dd8-a4cb-e1ea2bb332a5]]></Field>
 <Field name="RefObjFQName" type="java.lang.String"><![CDATA[WAREHOUSE_DATASOURCE.PROD7.GER.GER_GENERAL_EVENT.ID]]></Field>
 <Field name="RefObjFQType" type="java.lang.String"><![CDATA[SNP_MODFOLDER.SNP_MODEL.SNP_SUBMODEL.SNP_TABLE.SNP_COL]]></Field>
 <Field name="RefObjFQNameLengths" type="java.lang.String"><![CDATA[20.5.3.17.2]]></Field>
</Object>
<Object class="com.sunopsis.dwg.DwgExportSummary">
		<Field name="ExpTxtNb" type="com.sunopsis.sql.DbInt"><![CDATA[0]]></Field>
	<Field name="InstObjNb" type="com.sunopsis.sql.DbInt"><![CDATA[0]]></Field>
	<Field name="JoinColNb" type="com.sunopsis.sql.DbInt"><![CDATA[1]]></Field>
	<Field name="JoinNb" type="com.sunopsis.sql.DbInt"><![CDATA[1]]></Field>
	<Field name="KeyColNb" type="com.sunopsis.sql.DbInt"><![CDATA[1]]></Field>
	<Field name="KeyNb" type="com.sunopsis.sql.DbInt"><![CDATA[1]]></Field>
	<Field name="LinkDiagNb" type="com.sunopsis.sql.DbInt"><![CDATA[0]]></Field>
	<Field name="MorigTxtNb" type="com.sunopsis.sql.DbInt"><![CDATA[0]]></Field>
	<Field name="MtxtNb" type="com.sunopsis.sql.DbInt"><![CDATA[0]]></Field>
	<Field name="OrigTxtNb" type="com.sunopsis.sql.DbInt"><![CDATA[0]]></Field>
	<Field name="OtherObjectsNb" type="com.sunopsis.sql.DbInt"><![CDATA[22]]></Field>
	<Field name="PlanAgentNb" type="com.sunopsis.sql.DbInt"><![CDATA[0]]></Field>
	<Field name="StepNb" type="com.sunopsis.sql.DbInt"><![CDATA[0]]></Field>
	<Field name="TxtNb" type="com.sunopsis.sql.DbInt"><![CDATA[0]]></Field>
	<Field name="UeOrigNb" type="com.sunopsis.sql.DbInt"><![CDATA[0]]></Field>
	<Field name="UeUsedNb" type="com.sunopsis.sql.DbInt"><![CDATA[0]]></Field>
	<Field name="VarPlanAgentNb" type="com.sunopsis.sql.DbInt"><![CDATA[0]]></Field>
	<Field name="ScenTxtNb" type="com.sunopsis.sql.DbInt"><![CDATA[0]]></Field>
	<Field name="OdiVersion" type="java.lang.String"><![CDATA[12.2.1]]></Field>
	<Field name="OriginRepositoryID" type="com.sunopsis.sql.DbInt"><![CDATA[1]]></Field>
	<Field name="RepositoryVersion" type="java.lang.String"><![CDATA[05.02.02.07]]></Field>
</Object>
</SunopsisExport>
